Workbook

Sheet ENE23
A2: ENERO 2023 | C2: =C4+C68 -> 86444.12
A3: Fecha | B3: Concepto | C3: Monto
B4: MATERIALES | C4: =C5+C8+C11+C15+C20+C29+C34+C39+C44+C49+C52+C58+C61 -> 0
B5: Diesel para Buque | C5: =SUM(C6:C6) -> 0
B8: Gasolina para embarcaciones menores | C8: =SUM(C9) -> 0
B11: Gasolina para vehículos | C11: =SUM(C12:C13) -> 0
B15: Lubricantes | C15: =SUM(C16:C18) -> 0
B20: Víveres | C20: =SUM(C21:C27) -> 0
B29: Artículos y accesorios de cocina/limpieza | C29: =SUM(C30:C32) -> 0
B34: Mats. Para Mantto. De Cubiertas / Casco | C34: =SUM(C35:C37) -> 0
B39: Mats. Para Mantto. De Máquinas | C39: =SUM(C40:C42) -> 0
B44: Mats. Mantto. Embarcaciones Menores | C44: =SUM(C45:C47) -> 0
B49: Materiales para mantenimiento en dique seco | C49: =SUM(C50:C50) -> 0
B52: Equipo de seguridad y ayuda a la navegación | C52: =SUM(C53:C56) -> 0
B58: Mats. para laboratorios y electrónico | C58: =C59 -> 0
B61: Otros | C61: =SUM(C62:C65) -> 0
B68: SERVICIOS | C68: =C69+C73+C77+C80+C83+C86+C89+C92+C95+C98+C102+C105+C109+C115+C118+C124+C128+C146 -> 86444.12
B69: Mantenimiento a máquinas | C69: =SUM(C70:C71) -> 0
B73: Mantenimiento a cubiertas/casco | C73: =C74 -> 0
B77: Mantenimiento en dique seco | C77: =SUM(C78) -> 0
B80: Mantenimiento a embarcaciones menores | C80: =C81 -> 0
B83: Mantenimiento a vehículos terrestres | C83: =C84 -> 0
B86: Renta muelle | C86: =C87 -> 0
B89: Personal por Outsourcing | C89: =C90 -> 0
B92: Agenciamientos | C92: =C93 -> 0
B95: Limpieza de ropa de cama | C95: =SUM(C96:C96) -> 0
B98: Seguridad y ayuda a la navegación | C98: =SUM(C99:C100) -> 0
B102: Inspecciones ABS | C102: =C103 -> 0
B105: Mantenimiento a equipo científico y de laboratorio | C105: =SUM(C106:C107) -> 0
B109: Comunicaciones | C109: =SUM(C110:C113) -> 2091.36
A110: 13-Ene-23 | B110: TP79097 / Pago Telcel DEO Enero 2023 | C110: 1144.86
A111: 23-Ene-23 | B111: SS63379 / Repercusión INMARSAT BOAH Diciembre 2022 / Telecomunicaciones de México | C111: =25*18.93 -> 473.25
A112: 23-Ene-23 | B112: SS63384 / Repercusión INMARSAT BOAH Noviembre 2022 / Financiera para el bienestar | C112: =25*18.93 -> 473.25
B115: Parque vehicular CICESE | C115: =SUM(C116:C116) -> 1800
A116: 30-Ene-23 | B116: PV1052731 / TP79277 / Transportación con chofer al aeropuerto Tijuana enero 2023 | C116: 1800
B118: Comisiones/Servicios financieros/Pago de derechos | C118: =SUM(C119:C122) -> 218.76
A119: 23-Ene-23 | B119: SS63378 / Porcentaje repercusión INMARSAT BOAH Diciembre 2022 / Telecomunicaciones de México | C119: 108.99
A120: 23-Ene-23 | B120: SS63383 / Porcentaje repercusión INMARSAT BOAH Noviembre 2022 / Financiera para el bienestar | C120: 109.77
B124: Fletes diversos | C124: =SUM(C125:C126) -> 0
B128: Viáticos | C128: =SUM(C129:C144) -> 82334
A129: 23-Ene-23 | B129: SV109735 / Pedro Nuñez Cota / Tuxpan, Ver. / Boleto avión | C129: 6393
A130: 23-Ene-23 | B130: SV109735 / Pedro Nuñez Cota / Tuxpan, Ver. / Viáticos | C130: 513
A131: 23-Ene-23 | B131: SV109736 / Carlos Enrique Ortiz de los Santos / Tuxpan, Ver. / Boleto avión | C131: 6393
A132: 23-Ene-23 | B132: SV109736 / Carlos Enrique Ortiz de los Santos / Tuxpan, Ver. / Viáticos | C132: 513
A133: 23-Ene-23 | B133: SV109737 / Julio Cesar Nuñez Zamudio / Tuxpan, Ver. / Boleto avión | C133: 6393
A134: 23-Ene-23 | B134: SV109737 / Julio Cesar Nuñez Zamudio / Tuxpan, Ver. / Viáticos | C134: 513
A135: 23-Ene-23 | B135: SV109738 / Erick Rafael Rivera Lemus / Tuxpan, Ver. / Boleto avión | C135: 11816
A136: 23-Ene-23 | B136: SV109738 / Erick Rafael Rivera Lemus / Tuxpan, Ver. / Viáticos y renta transporte | C136: 49800
B146: Otros | C146: =SUM(C147:C150) -> 0
B153: INVERSION | C153: =SUM(C154:C154) -> 0

Sheet FEB23
A2: FEBRERO 2023 | C2: =C4+C92 -> 424910.57
A3: Fecha | B3: Concepto | C3: Monto
B4: MATERIALES | C4: =C5+C10+C15+C22+C27+C34+C40+C49+C59+C66+C69+C79+C82 -> 82962.285
B5: Diesel para Buque | C5: =SUM(C6:C8) -> 0
B10: Gasolina para embarcaciones menores | C10: =SUM(C11:C13) -> 0
B15: Gasolina para vehículos | C15: =SUM(C16:C20) -> 0
B22: Lubricantes | C22: =SUM(C23:C25) -> 0
B27: Víveres | C27: =SUM(C28:C32) -> 51219.93
A28: 44974 | B28: SA85117 / Avit. De víveres al BOAH para estancia Feb23 / Ruvaships, S. A. de C. V. | C28: 30900
A29: 44966 | B29: GRC103199 / Avit. Víveres para estancia enero 2023 | C29: 18461.8
A30: 44964 | B30: OC20230062 / Avit. Víveres para estancia enero 2023 | C30: 1858.13
B34: Artículos y accesorios de cocina/limpieza | C34: =SUM(C35:C38) -> 0
B40: Mats. Para Mantto. De Cubiertas / Casco | C40: =SUM(C41:C46) -> 0
B49: Mats. Para Mantto. De Máquinas | C49: =SUM(C50:C57) -> 22969.345
A50: 44965 | B50: SA85055 / Químico preservativo de membranas y flujómetro para desaladora BOAH / Agencia Arjona, S. A. de C. V. | C50: =1048.68*18.89 -> 19809.565
A51: 44966 | B51: GRC103199 / Tubo y niple, soldadura, grasera, grapas | C51: =2092.01+667.78+399.99 -> 3159.78
B59: Mats. Mantto. Embarcaciones Menores | C59: =SUM(C60:C64) -> 4168.55
A60: 44972 | B60: RFF11699 / Madera para remolque Antares, fusibles Rigel, herrería remolque Antares | C60: =1631.15+614.01+545.01+331.18+594+171.23+188+44.5+49.47 -> 4168.55
B66: Materiales para mantenimiento en dique seco | C66: =SUM(C67) -> 0
B69: Equipo de seguridad y ayuda a la navegación | C69: =SUM(C70:C77) -> 0
B79: Mats. para laboratorios y electrónico | C79: =C80 -> 0
B82: Otros | C82: =SUM(C83:C89) -> 4604.46
A83: 44972 | B83: RFF11699 / Aceite transmisión y motor para 15C, calendario pared DEO 2023 | C83: =2652.83+1102.89+418.74 -> 4174.46
A84: 44964 | B84: OC20230062 / Papelería y madera | C84: =244.4+185.6 -> 430
B92: SERVICIOS | C92: =C93+C101+C104+C107+C116+C119+C125+C129+C133+C137+C142+C145+C150+C168+C175+C182+C187+C213 -> 341948.28
B93: Mantenimiento a máquinas | C93: =SUM(C94:C99) -> 32110
A94: 44977 | B94: SS63548 / Mantenimiento a sistemas A/C BOAH Feb23 / Bernardino Telésforo Nuñez | C94: 25288
A95: 44967 | B95: OC20230081 / Mantenimiento a motor eléctrico BOAH | C95: =6822 -> 6822
B101: Mantenimiento a cubiertas/casco | C101: =C102 -> 0
B104: Mantenimiento en dique seco | C104: =SUM(C105) -> 0
B107: Mantenimiento a embarcaciones menores | C107: =SUM(C108:C114) -> 0
B116: Mantenimiento a vehículos terrestres | C116: =C117 -> 0
B119: Renta muelle | C119: =SUM(C120:C123) -> 0
B125: Personal por Outsourcing | C125: =C126 -> 199942.59
A126: 44985 | B126: SS63592 / Personal por outsourcing BOAH enero 2023 / Ingeniería del agua y medio ambiente, S. C. | C126: 199942.59
B129: Agenciamientos | C129: =SUM(C130:C131) -> 0
B133: Limpieza de ropa de cama | C133: =SUM(C134:C135) -> 0
B137: Seguridad y ayuda a la navegación | C137: =SUM(C138:C140) -> 0
B142: Inspecciones ABS | C142: 0
B145: Mantenimiento a equipo científico y de laboratorio | C145: =SUM(C146:C148) -> 0
B150: Comunicaciones | C150: =SUM(C151:C166) -> 1145.77
A151: 44970 | B151: TP79636 / Pago Telcel DEO | C151: 1145.77
B168: Parque vehicular CICESE | C168: =SUM(C169:C173) -> 3586.72
A169: 44980 | B169: TP79827 / PV1052790 / Transportación con chofer del aeropuerto Tijuana 17feb23 | C169: 1485.12
A170: 44980 | B170: TP79820 / PV1052773 / Transportación con chofer al aeropuerto Tijuana 15feb23 | C170: 1101.6
A171: 44970 | B171: TP79612 / PV1052732 / Transportación con chofer del aeropuerto 03feb23 | C171: 1000
B175: Comisiones/Servicios financieros/Pago de derechos | C175: =SUM(C176:C180) -> 4698
A176: 44960 | B176: OC20230047 / Reembolso gastos renovación libreta de mar JCNZ | C176: 4698
B182: Fletes diversos | C182: =SUM(C183:C185) -> 18699.2
A183: 44970 | B183: SS63490 / Recolección, traslado y confinamiento de aceite residual BOAH Feb23 / Reco Cero, S. A. de C. V. | C183: 18699.2
B187: Viáticos | C187: =SUM(C188:C211) -> 81766
A188: 8-Feb-23 | B188: SV109854 / Ivan Castro Navarro / Salida Rigel 10feb23 | C188: 300
A189: 8-Feb-23 | B189: SV109856 / Rosario Félix Reyes / Salida Rigel 10feb23 | C189: 300
A190: 8-Feb-23 | B190: SV109857 / Juan Carlos Leñero Vazquez / Salida Rigel 10feb23 | C190: 300
A191: 10-Feb-23 | B191: SV109874 / Marco Antonio Castillo Ramírez / Tuxpan, Ver 15feb23 / Boleto avion | C191: 3106
A192: 10-Feb-23 | B192: SV109874 / Marco Antonio Castillo Ramírez / Tuxpan, Ver 15feb23 / Viáticos | C192: =513+950 -> 1463
A193: 10-Feb-23 | B193: SV109875 / Gustavo Castro Navarro / Tuxpan, Ver 15feb23 / Boleto avion | C193: 3106
A194: 10-Feb-23 | B194: SV109875 / Gustavo Castro Navarro / Tuxpan, Ver 15feb23 / Viáticos | C194: =513+550 -> 1063
A195: 10-Feb-23 | B195: SV109876 / Rosario Félix Reyes / Tuxpan, Ver 15feb23 / Boleto avion | C195: 3106
A196: 10-Feb-23 | B196: SV109876 / Rosario Félix Reyes / Tuxpan, Ver 15feb23 / Viáticos | C196: =513+550 -> 1063
A197: 14-Feb-23 | B197: SV109912 / Ivan Castro Navarro / Salida Rigel 17feb23 | C197: 300
A198: 14-Feb-23 | B198: SV109913 / Juan Carlos Leñero Vazquez / Salida Rigel 17feb23 | C198: 300
A199: 16-Feb-23 | B199: SV109927 / Pedro Nuñez Cota / Ensenada, B. C. 17feb23 / Boleto avión | C199: 3102
A200: 16-Feb-23 | B200: SV109927 / Pedro Nuñez Cota / Ensenada, B. C. 17feb23 / Viáticos | C200: =950+513 -> 1463
A201: 16-Feb-23 | B201: SV109932 / Carlos Enrique Ortiz de los Santos / Ensenada, B. C. 17feb23 / Boleto avión | C201: 3102
A202: 16-Feb-23 | B202: SV109932 / Carlos Enrique Ortiz de los Santos / Ensenada, B. C. 17feb23 / Viáticos | C202: =513+550 -> 1063
A203: 16-Feb-23 | B203: SV109933 / Julio César Nuñez Zamudio / Ensenada, B. C. 17feb23 / Boleto avión | C203: 3672
A204: 16-Feb-23 | B204: SV109933 / Julio César Nuñez Zamudio / Ensenada, B. C. 17feb23 / Viáticos | C204: =513+550 -> 1063
A205: 20-Feb-23 | B205: SV109982 (624126) / Ivan Castro Navarro / Salida Rigel 21feb23 | C205: 300
A206: 20-Feb-23 | B206: SV109981 (624126) / Juan Carlos Leñero / Salida Rigel 21feb23 | C206: 300
A207: 22-Feb-23 | B207: SV109993 / Erick Rafael Rivera Lemus / Tuxpan, Ver 26feb-05mar23 / Boletos avión | C207: 10344
A208: 22-Feb-23 | B208: SV109993 / Erick Rafael Rivera Lemus / Tuxpan, Ver 26feb-05mar23 / Viáticos | C208: 42950
B213: Otros | C213: =SUM(C214:C221) -> 0
B225: INVERSION | C225: =SUM(C226:C226) -> 0

Sheet MAR23
A2: MARZO 2023 | C2: =C4+C87 -> 827814.76
A3: Fecha | B3: Concepto | C3: Monto
B4: MATERIALES | C4: =C5+C10+C19+C24+C28+C37+C45+C52+C60+C66+C70+C75+C80 -> 41356.3
B5: Diesel para Buque | C5: =SUM(C6:C8) -> 0
B10: Gasolina para embarcaciones menores | C10: =SUM(C11:C17) -> 0
B19: Gasolina para vehículos | C19: =SUM(C20:C22) -> 2128.03
A20: 45012 | B20: SV110287 / Gasolina para viaje a BLA | C20: 2128.03
B24: Lubricantes | C24: =SUM(C25:C26) -> 0
B28: Víveres | C28: =SUM(C29:C35) -> 21315
A29: 45009 | B29: SA85440 / Avit. Víveres para estancia personal Mar23 / Ruvaships, S. A. de C. V. | C29: 21315
B37: Artículos y accesorios de cocina/limpieza | C37: =SUM(C38:C43) -> 3584.26
A38: 45016 | B38: SA85497 / Materiales de limpieza para buque / Ruvaships, S. A. de C. V. | C38: 3584.26
B45: Mats. Para Mantto. De Cubiertas / Casco | C45: =SUM(C46:C50) -> 0
B52: Mats. Para Mantto. De Máquinas | C52: =SUM(C53:C58) -> 14329.01
A53: 44999 | B53: GRC103224 / Triplays en Tuxpan para máquinas BOAH, tubería y soldadura | C53: =2600.01+6519 -> 9119.01
A54: 45006 | B54: OC20230253 / Baterías para UPS BOAH mar23 | C54: 5210
B60: Mats. Mantto. Embarcaciones Menores | C60: =SUM(C61:C64) -> 0
B66: Materiales para mantenimiento en dique seco | C66: =SUM(C67:C68) -> 0
B70: Equipo de seguridad y ayuda a la navegación | C70: =SUM(C71:C73) -> 0
B75: Mats. para laboratorios y electrónico | C75: =SUM(C76:C78) -> 0
B80: Otros | C80: =SUM(C81:C84) -> 0
B87: SERVICIOS | C87: =C88+C95+C98+C101+C104+C107+C111+C114+C119+C123+C127+C130+C133+C142+C151+C159+C164+C192 -> 786458.46
B88: Mantenimiento a máquinas | C88: =SUM(C89:C93) -> 0
B95: Mantenimiento a cubiertas/casco | C95: =SUM(C96:C96) -> 0
B98: Mantenimiento en dique seco | C98: =SUM(C99) -> 0
B101: Mantenimiento a embarcaciones menores | C101: =SUM(C102) -> 0
B104: Mantenimiento a vehículos terrestres | C104: =SUM(C105) -> 0
B107: Renta muelle | C107: =SUM(C108:C109) -> 496154.73
A108: 45000 | B108: SS63727 / Renta muelle y energía eléctrica BOAH febrero 2023 / Compañía Mexicana de Soluciones Onshore, S. de R. L. de C. V. | C108: 246053.56
A109: 45000 | B109: SS63726 / Renta muelle y energía eléctrica BOAH enero 2023 / Compañía Mexicana de Soluciones Onshore, S. de R. L. de C. V. | C109: 250101.17
B111: Personal por Outsourcing | C111: =SUM(C112) -> 201205.49
A112: 45015 | B112: SS63837 / Personal por Outsourcing BOAH marzo 2023 / Arkadiarium, S. A. de C. V. | C112: 201205.49
B114: Agenciamientos | C114: =SUM(C115:C117) -> 0
B119: Limpieza de ropa de cama | C119: =SUM(C120:C121) -> 0
B123: Seguridad y ayuda a la navegación | C123: =SUM(C124:C125) -> 0
B127: Inspecciones ABS | C127: =SUM(C128) -> 0
B130: Mantenimiento a equipo científico y de laboratorio | C130: =SUM(C131) -> 0
B133: Comunicaciones | C133: =SUM(C134:C140) -> 3148.63
A134: 45009 | B134: SS63784 / Repercusión INMARSAT BOAH Febrero 2023 / Financiera del Bienestar | C134: =55*18.23 -> 1002.65
A135: 44995 | B135: SS63700 / Repercusión INMARSAT BOAH Enero 2023 / Financiera del Bienestar | C135: =55*18.2 -> 1001
A136: 44999 | B136: TP80090 / Pago Telcel DEO | C136: 1144.98
B142: Parque vehicular CICESE | C142: =SUM(C143:C149) -> 7235.59
A143: 45012 | B143: TP80345 / PV1052888 / Transportación con chofer a aeropuerto Tijuana 20-21mar23 | C143: 1886.58
A144: 45000 | B144: TP80148 / PV1052863 / Transportación con chofer de aeropuerto Tijuana 10mar23 | C144: 2133.52
A145: 45000 | B145: TP80126 / PV1052806 / Transportación con chofer de aeropuerto Tijuana 05mar23 | C145: 1631.83
A146: 44988 | B146: TP79941 / PV1052805 / Transportación con chofer al aeropuerto Tijuana 26feb23 | C146: 1583.66
B151: Comisiones/Servicios financieros/Pago de derechos | C151: =SUM(C152:C157) -> 3284.6
A152: 45009 | B152: SS63783 / Porcentaje de repercusión INMARSAT BOAH Febrero 2023 / Financiera del Bienestar | C152: 242.41
A153: 44995 | B153: SS63701 / Porcentaje de repercusión INMARSAT BOAH Enero 2023 / Financiera del Bienestar | C153: 234.75
A154: 45006 | B154: TP80247 / Pago derechos placas remolque Rigel y unidad 15-C | C154: 2807.44
B159: Fletes diversos | C159: =SUM(C160:C162) -> 0
B164: Viáticos | C164: =SUM(C165:C190) -> 63365.42
A165: 1-Mar-23 | B165: SV110065 (624126) / Juan Carlos Leñero Vazquez / Salida Rigel 03mar23 | C165: 300
A166: 1-Mar-23 | B166: SV110066 (624126) / Ivan Castro Navarro / Salida Rigel 03mar23 | C166: 300
A167: 1-Mar-23 | B167: SV110067 (624126) / José Ramón López Chico / Salida Rigel 03mar23 | C167: 300
A168: 8-Mar-23 | B168: SV110105 (624126) / Juan Carlos Leñero Vazquez / Salida Rigel 09mar23 | C168: =297.5 -> 297.5
A169: 8-Mar-23 | B169: SV110106 (624126) / Ivan Castro Navarro / Salida Rigel 09mar23 | C169: 300
A170: 10-Mar-23 | B170: SV110141 / Rosario Félix Reyes / Ensenada, B. C. 10mar23 / Boleto avión | C170: 6279
A171: 10-Mar-23 | B171: SV110141 / Rosario Félix Reyes / Ensenada, B. C. 10mar23 / Viáticos | C171: 786.99
A172: 10-Mar-23 | B172: SV110142 / Marco Antonio Castillo Ramírez / Ensenada, B. C. 10mar23 / Boleto avión | C172: 5360
A173: 10-Mar-23 | B173: SV110142 / Marco Antonio Castillo Ramírez / Ensenada, B. C. 10mar23 / Viáticos | C173: 988.51
A174: 10-Mar-23 | B174: SV110143 / Gustavo Castro Navarro / Ensenada, B. C. 10mar23 / Boleto avión | C174: 5360
A175: 10-Mar-23 | B175: SV110143 / Gustavo Castro Navarro / Ensenada, B. C. 10mar23 / Viáticos | C175: 1134.02
A176: 27-Mar-23 | B176: SV110289 / Ivan Castro Navarro / Salida a BLA 28-29mar23 | C176: 1763
A177: 27-Mar-23 | B177: SV110287 / Juan Carlos Leñero Vazquez / Salida a BLA 28-29mar23 | C177: 1743.9
A178: 17-Mar-23 | B178: SV110231 / Julio César Nuñez Zamudio / ENS-TUX-ENS 21-31mar23 / Boleto avión | C178: 10239
A179: 17-Mar-23 | B179: SV110231 / Julio César Nuñez Zamudio / ENS-TUX-ENS 21-31mar23 / Viáticos | C179: =975.5+1152 -> 2127.5
A180: 17-Mar-23 | B180: SV110230 / Carlos Enrique Ortiz de los Santos / ENS-TUX-ENS 21-31mar23 / Boleto avión | C180: 10229
A181: 17-Mar-23 | B181: SV110230 / Carlos Enrique Ortiz de los Santos / ENS-TUX-ENS 21-31mar23 / Viáticos | C181: 2178
A182: 17-Mar-23 | B182: SV110229 / Pedro Nuñez Cota / ENS-TUX-EBS 21-31mar23 / Boleto avión | C182: 10239
A183: 17-Mar-23 | B183: SV110229 / Pedro Nuñez Cota / ENS-TUX-EBS 21-31mar23 / Viáticos | C183: 2570
A184: 17-Mar-23 | B184: SV110228 (624126) / Juan Carlos Leñero Vazquez / Salida Rigel 17mar23 | C184: 300
A185: 17-Mar-23 | B185: SV110227 (624126) / Ivan Castro Navarro / Salida Rigel 17mar23 | C185: 300
A186: 22-Mar-23 | B186: OC20230255 (624126) / Reembolso viáticos ICN salida a EPB ICN 02mar23 | C186: 270
B192: Otros | C192: =SUM(C193:C198) -> 12064
A193: 45000 | B193: SS63730 / Póliza seguro externos DEO 2023 / AIG Seguros México, S. A. de C. V. | C193: 12064
B201: INVERSION | C201: =C202 -> 0

Sheet ABR23
A2: ABRIL 2023 | C2: =C4+C93 -> 1084325.5
A3: Fecha | B3: Concepto | C3: Monto
B4: MATERIALES | C4: =C5+C10+C18+C22+C28+C37+C45+C52+C61+C67+C75+C78+C81 -> 320226
B5: Diesel para Buque | C5: =SUM(C6:C8) -> 0
B10: Gasolina para embarcaciones menores | C10: =SUM(C11:C16) -> 0
B18: Gasolina para vehículos | C18: =SUM(C19:C20) -> 0
B22: Lubricantes | C22: =SUM(C23:C26) -> 0
B28: Víveres | C28: =SUM(C29:C35) -> 300601.64
A29: 26-Abr-23 | B29: SA85641 / Avit. Víveres crucero InstBOC y traslados TUX-COA y COA-TUX / Ruvaships, S. A. de C. V. | C29: 300601.64
B37: Artículos y accesorios de cocina/limpieza | C37: =SUM(C38:C43) -> 18195.06
A38: 26-Abr-23 | B38: SA85641 / Abast. Mats. Limp. Abr23 / Ruvaships, S. A. de C. V. | C38: 18195.06
B45: Mats. Para Mantto. De Cubiertas / Casco | C45: =SUM(C46:C50) -> 0
B52: Mats. Para Mantto. De Máquinas | C52: =SUM(C53:C59) -> 0
B61: Mats. Mantto. Embarcaciones Menores | C61: =SUM(C62:C65) -> 0
B67: Materiales para Mantenimiento en Dique Seco | C67: =SUM(C68:C73) -> 0
B75: Equipo de seguridad y ayuda a la navegación | C75: =C76 -> 0
B78: Mats. para laboratorios y electrónico | C78: =C79 -> 0
B81: Otros | C81: =SUM(C82:C90) -> 1429.3
A82: 13-Abr-23 | B82: SA85541 / Materiales para mesita de café del DEO / Smart and Final del Noroeste, S. A. de C. V. | C82: 1429.3
B93: SERVICIOS | C93: =C94+C102+C108+C111+C116+C119+C122+C126+C131+C134+C137+C140+C144+C153+C162+C169+C174+C215 -> 764099.49
B94: Mantenimiento a máquinas | C94: =SUM(C95:C100) -> 0
B102: Mantenimiento a cubiertas/casco | C102: =SUM(C103:C106) -> 0
B108: Mantenimiento en dique seco | C108: =SUM(C109) -> 0
B111: Mantenimiento a embarcaciones menores | C111: =SUM(C112:C114) -> 0
B116: Mantenimiento a vehículos terrestres | C116: =SUM(C117) -> 4958.28
A117: 10-Abr-23 | B117: SS63866 / Cambio de bujías, dos coils y lavado inyectores motor 15-C / René López Magdaleno | C117: 4958.28
B119: Renta muelle | C119: =C120 -> 273225.54
A120: 11-Abr-23 | B120: SS63874 / Renta muelle y energía eléctrica del mes de marzo 2023 / Compañía Mexicana de Soluciones Onshore, S. de R. L. de C. V. | C120: 273225.54
B122: Personal por Outsourcing | C122: =SUM(C123:C124) -> 400220.14
A123: 28-Abr-23 | B123: SS64058 / Personal por outsourcing BOAH abr23 / Arkadiarium, S. A. de C. V. | C123: 201205.51
A124: 12-Abr-23 | B124: SS63891 / Personal por Outsourcing BOAH feb23 / Ingeniería del Agua y Medio Ambiente, S. C. | C124: 199014.63
B126: Agenciamientos | C126: =SUM(C127:C129) -> 0
B131: Limpieza de ropa de cama | C131: =SUM(C132:C132) -> 0
B134: Seguridad y ayuda a la navegación | C134: =SUM(C135:C135) -> 0
B137: Inspecciones ABS | C137: =C138 -> 0
B140: Mantenimiento a equipo científico y de laboratorio | C140: =SUM(C141:C142) -> 0
B144: Comunicaciones | C144: =SUM(C145:C151) -> 1145.98
A145: 13-Abr-23 | B145: TP80569 / Pago Telcel DEO | C145: 1145.98
B153: Parque vehicular CICESE | C153: =SUM(C154:C160) -> 7090.07
A154: 10-Abr-23 | B154: TP80495 / PV1052915 / Renta unidad 3D viaje a BLA marzo 2023 | C154: 1200
A155: 10-Abr-23 | B155: TP80510 / PV1052934 / Transportación con chofer de Tijuana a Ensenada 31mar23 | C155: 1931.44
A156: 21-Abr-23 | B156: TP80741 / PV1052992 / Transportación con chofer al Aeropuerto de Tijuana 24abr23 | C156: 2258.63
A157: 21-Abr-23 | B157: TP80834 / PV1052994 / Transportación con chofer al Aeropuerto de Tijuana 25abr23 | C157: 1000
A158: 24-Abr-23 | B158: TP80982 / PV1053000 / Transportación con chofer del Aeropuerto de Tijuana 27abr23 | C158: 700
B162: Comisiones/Servicios financieros/Pago de derechos | C162: =SUM(C163:C167) -> 0
B169: Fletes diversos | C169: =SUM(C170:C172) -> 0
B174: Viáticos | C174: =SUM(C175:C213) -> 77459.48
A175: 11-Abr-23 | B175: SV110397 (624126) / Juan Carlos Leñero Vazquez / Salida Rigel 11abr23 | C175: 300
A176: 11-Abr-23 | B176: SV110356 (624126) / José Ramón López Chico / Salida Rigel 11abr23 | C176: 300
A177: 13-Abr-23 | B177: SV110422 (624126) / Juan Carlos Leñero Vazquez / Salida Rigel 19abr23 | C177: 300
A178: 13-Abr-23 | B178: SV110423 (624126) / Ivan Castro Navarro / Salida Rigel 19abr23 | C178: 300
A179: 13-Abr-23 | B179: SV110425 (624126) / Ivan Castro Navarro / Salida Rigel 24abr23 | C179: 300
A180: 13-Abr-23 | B180: SV110426 (624126) / Juan Carlos Leñero Vazquez / Salida Rigel 24abr23 | C180: 300
A181: 13-Abr-23 | B181: SV110427 (624126) / Juan Carlos Leñero Vazquez / Salida Rigel 25may23 | C181: 300
A182: 27-Abr-23 | B182: SV110587 / Erick Rafael Rivera Lemus / TUX-COA y estancia COA pre-crucero abr-may23 | C182: 6266.59
A183: 24-Abr-23 | B183: SV110551 / José Ramón López Chico / TUX-ENS 27abr23 (Boleto avión) | C183: 7154
A184: 24-Abr-23 | B184: SV110551 / José Ramón López Chico / TUX-ENS 27abr23 (Viáticos) | C184: 1285
A185: 20-Abr-23 | B185: SV110502 / Erick Rafael Rivera Lemus / ENS-TUX 25abr23 (Boleto avión) | C185: 7890
A186: 20-Abr-23 | B186: SV110502 / Erick Rafael Rivera Lemus / ENS-TUX 25abr23 (Viáticos) | C186: 1312
... A189: 20-Abr-23 | B189: SV110500 / José Ramón López Chico / ENS-TUX 24abr23 (Boleto avión) | C189: 6159
A190: 20-Abr-23 | B190: SV110500 / José Ramón López Chico / ENS-TUX 24abr23 (Viáticos) | C190: =513+576 -> 1089
A191: 20-Abr-23 | B191: SV110499 / Gustavo Castro Navarro / ENS-TUX 24abr23 (Boleto avión) | C191: 5409
A192: 20-Abr-23 | B192: SV110499 / Gustavo Castro Navarro / ENS-TUX 24abr23 (Viáticos) | C192: 1089
A193: 20-Abr-23 | B193: SV110498 / Marco Antonio Castillo Ramírez / ENS-TUX 24abr23 (Boleto avión) | C193: 5409
A194: 20-Abr-23 | B194: SV110498 / Marco Antonio Castillo Ramírez / ENS-TUX 24abr23 (Viáticos) | C194: 1087
A195: 20-Abr-23 | B195: SV110497 / Julio César Nuñez Zamudio / ENS-TUX 24abr23 (Boleto avión) | C195: 6159
A196: 20-Abr-23 | B196: SV110497 / Julio César Nuñez Zamudio / ENS-TUX 24abr23 (Viáticos) | C196: 1089
A197: 20-Abr-23 | B197: SV110496 / Carlos Enrique Ortiz de los Santos / ENS-TUX 24abr23 (Boleto avión) | C197: 5409
A198: 20-Abr-23 | B198: SV110496 / Carlos Enrique Ortiz de los Santos / ENS-TUX 24abr23 (Viáticos) | C198: =576+513 -> 1089
A199: 20-Abr-23 | B199: SV110495 / Pedro Nuñez Cota / ENS-TUX 24abr23 (Boleto avión) | C199: 5409
A200: 20-Abr-23 | B200: SV110495 / Pedro Nuñez Cota / ENS-TUX 24abr23 (Viáticos) | C200: =1172+513 -> 1685
A201: 14-Abr-23 | B201: SV110433 (624126) / Ivan Castro Navarro / Salida Rigel 25-may-23 | C201: 300
A202: 18-Abr-23 | B202: OC20230353 (624126) / Reembolso viáticos ICN salida 11abr23 | C202: 324.89
B215: Otros | C215: =SUM(C216:C221) -> 0
B224: INVERSION | C224: =SUM(C225:C228) -> 0

Sheet MAY23
A2: MAYO 2023 | C2: =C4+C95 -> 744699.78
A3: Fecha | B3: Concepto | C3: Monto
B4: MATERIALES | C4: =C5+C9+C18+C26+C31+C40+C46+C54+C63+C70+C76+C82+C86 -> 44821.422
B5: Diesel para Buque | C5: =SUM(C6:C7) -> 0
B9: Gasolina para embarcaciones menores | C9: =SUM(C10:C16) -> 7491.45
A10: 45070 | B10: RFF11822 / Gasolina Rigel | C10: =2806.38+1700.07+2985 -> 7491.45
B18: Gasolina para vehículos | C18: =SUM(C19:C24) -> 1212.72
A19: 45070 | B19: RFF11822 / Gasolina 15-C | C19: 1212.72
B26: Lubricantes | C26: =SUM(C27:C29) -> 0
B31: Víveres | C31: =SUM(C32:C38) -> 0
B40: Artículos y accesorios de cocina/limpieza | C40: =SUM(C41:C44) -> 0
B46: Mats. Para Mantto. De Cubiertas / Casco | C46: =SUM(C47:C52) -> 2300.61
A47: 45070 | B47: RFF11822 / Banderas Mexicanas | C47: =1135.61 -> 1135.61
A48: 45057 | B48: OC20230438 / Ventilador Man Caf | C48: 1165
B54: Mats. Para Mantto. De Máquinas | C54: =SUM(C55:C61) -> 16564.82
A55: 45068 | B55: SA85852 / Dos piquetas y puntas para mantenimiento BOAH / Agencia Arjona, S. A. de C. V. | C55: 16564.82
B63: Mats. Mantto. Embarcaciones Menores | C63: =SUM(C64:C68) -> 0
B70: Materiales para Mantenimiento en Dique Seco | C70: =SUM(C71:C74) -> 0
B76: Equipo de seguridad y ayuda a la navegación | C76: =SUM(C77:C80) -> 11861.502
A77: 45069 | B77: SA85867 / 28 Luces estrobo para chalecos de emergencia BOAH / Agencia Arjona, S. A. de C. V. | C77: =660.44*17.96 -> 11861.502
B82: Mats. para laboratorios y electrónico | C82: =SUM(C83:C84) -> 0
B86: Otros | C86: =SUM(C87:C92) -> 5390.32
A87: 45070 | B87: RFF11822 / Baterías para UPSs oficina DEO, discos abrasivos para quitar base de poste patio trasero | C87: =95.32+780+935 -> 1810.32
A88: 45057 | B88: OC20230438 / Medicamentos botiquín BOAH | C88: 3580
B95: SERVICIOS | C95: =C96+C103+C109+C112+C117+C120+C124+C127+C132+C135+C138+C141+C144+C153+C159+C165+C170+C197 -> 699878.36
B96: Mantenimiento a máquinas | C96: =SUM(C97:C101) -> 234830.4
A97: 45068 | B97: SS64280 / Mantenimiento a 4 baños del BOAH / Ruvaships, S. A. de C. V. | C97: 234830.4
B103: Mantenimiento a cubiertas/casco | C103: =SUM(C104:C107) -> 0
B109: Mantenimiento en dique seco | C109: =SUM(C110) -> 0
B112: Mantenimiento a embarcaciones menores | C112: =SUM(C113:C115) -> 0
B117: Mantenimiento a vehículos terrestres | C117: =SUM(C118) -> 2808
A118: 45057 | B118: SS64164 / Mantenimiento a radiador 15-C / Esther Marina Parra Mora | C118: 2808
B120: Renta muelle | C120: =SUM(C121:C122) -> 253369.62
A121: 45054 | B121: SS64131 / Renta muelle BOAH Tuxpan Abril 2023 / Compañía Mexicana de Soluciones Onshore, S. de R. L. de C. V. | C121: 253369.62
B124: Personal por Outsourcing | C124: =C125 -> 0
B127: Agenciamientos | C127: =SUM(C128:C130) -> 11600
A128: 45055 | B128: SS64139 / Agenciamientos para traslado TUX-COA abril 2023 / Tajin Consignaciones, S. A. de C. V. | C128: 11600
B132: Limpieza de ropa de cama | C132: =SUM(C133:C133) -> 2811
A133: 45061 | B133: GRC103283 / Limpieza de ropa de cama en TUX previo cruceros | C133: 2811
B135: Seguridad y ayuda a la navegación | C135: =SUM(C136:C136) -> 0
B138: Inspecciones ABS | C138: =SUM(C139:C139) -> 60774.52
A139: 30-May-23 | B139: SS64337 / Inspecciones anuales 2023 / American Bureau of Shipping | C139: 60774.52
B141: Mantenimiento a equipo científico y de laboratorio | C141: =C142 -> 0
B144: Comunicaciones | C144: =SUM(C145:C151) -> 1410.89
A145: 45058 | B145: TP81066 (624108) / Pago Telcel DEO Mayo 2023 | C145: 1144.98
A146: 45076 | B146: TP81489 / Cobro telefonía interna | C146: 265.91
B153: Parque vehicular CICESE | C153: =SUM(C154:C157) -> 2661.29
A154: 45064 | B154: TP81350 / PV1053078 / Transportación del aeropuerto de Tijuana 20may23 | C154: 2661.29
B159: Comisiones/Servicios financieros/Pago de derechos | C159: =SUM(C160:C163) -> 69215.44
A160: 45076 | B160: GRC103291 / Pago derechos en Tuxpan y Coatza operaciones BOAH abr-may23 | C160: 54791.35
A161: 45061 | B161: GRC103283 / Pago derechos, sanidad y lanchaje | C161: =6197.74+5220+282.35+1816+908 -> 14424.09
B165: Fletes diversos | C165: =SUM(C166:C168) -> 0
B170: Viáticos | C170: =SUM(C171:C195) -> 58402
A171: 19-May-23 | B171: SV110770 (624126) / Viáticos salida Rigel 23-May-23 / Ivan Castro Navarro | C171: 300
A172: 19-May-23 | B172: SV110769 (624126) / Viáticos salida Rigel 23-May-23 / Juan Carlos Leñero Vazquez | C172: 300
A173: 19-May-23 | B173: SV110768 / Juan Carlos Leñero Vazquez / TUX-ENS 20may23 / Boleto avión | C173: 7487
A174: 19-May-23 | B174: SV110768 / Juan Carlos Leñero Vazquez / TUX-ENS 20may23 / Viáticos | C174: 1105
A175: 19-May-23 | B175: SV110758 / Julio César Nuñez Zamudio / TUX-ENS 20may23 / Boleto avión | C175: 7487
A176: 19-May-23 | B176: SV110758 / Julio César Nuñez Zamudio / TUX-ENS 20may23 / Viáticos | C176: =513+592 -> 1105
A177: 19-May-23 | B177: SV110757 / Marco Antonio Castillo Ramírez / TUX-ENS 20may23 / Boleto avión | C177: 6752
A178: 19-May-23 | B178: SV110757 / Marco Antonio Castillo Ramírez / TUX-ENS 20may23 / Viáticos | C178: 1105
A179: 19-May-23 | B179: SV110756 / Gustavo Castro Navarro / TUX-ENS 20may23 / Boleto avión | C179: 6752
A180: 19-May-23 | B180: SV110756 / Gustavo Castro Navarro / TUX-ENS 20may23 / Viáticos | C180: 1105
A181: 19-May-23 | B181: SV110755 / Carlos Enrique Ortiz de los Santos / TUX-ENS 20may23 / Boleto avión | C181: 6752
A182: 19-May-23 | B182: SV110755 / Carlos Enrique Ortiz de los Santos / TUX-ENS 20may23 / Viáticos | C182: 785
A183: 19-May-23 | B183: SV110754 / Pedro Nuñez Cota / TUX-ENS 20may23 / Boleto avión | C183: 6752
A184: 19-May-23 | B184: SV110754 / Pedro Nuñez Cota / TUX-ENS 20may23 / Viáticos | C184: 1105
A185: 19-May-23 | B185: SV110752 / Erick Rafael Rivera Lemus / TUX-ENS 20may23 / Boleto avión | C185: 6752
A186: 19-May-23 | B186: SV110752 / Erick Rafael Rivera Lemus / TUX-ENS 20may23 / Viáticos | C186: =750+592+400 -> 1742
A187: 11-May-23 | B187: OC20230438 / Boleto autobús Tuxpan - Coatza ERRL | C187: 1016
B197: Otros | C197: =SUM(C198:C202) -> 1995.2
A198: 45070 | B198: RFF11822 / Suministro de agua en pipa al BOAH | C198: 1995.2
B205: INVERSION | C205: =SUM(C206:C208) -> 12694.968
A206: 26-May-23 | B206: SA85905 (621808) / Ecosonda Simrad Cruise 9 para Rigel / Erick Rafael Rivera Lemus | C206: =712.8*17.81 -> 12694.968

Sheet JUN23
A2: JUNIO 2023 | C2: =C4+C90 -> 793877.75
A3: Fecha | B3: Concepto | C3: Monto
B4: MATERIALES | C4: =C5+C11+C18+C22+C27+C35+C48+C55+C65+C71+C74+C77+C80 -> 138477.37
B5: Diesel para Buque | C5: =SUM(C6:C9) -> 0
B11: Gasolina para embarcaciones menores | C11: =SUM(C12:C16) -> 0
B18: Gasolina para vehículos | C18: =SUM(C19:C20) -> 0
B22: Lubricantes | C22: =SUM(C23:C25) -> 43200
A23: 45085 | B23: SA86028 / 2 Tibores de aceite Phillips 66 T5X para motogens BOAH / Rudametkin Distribuidora, S. A. de C. V. | C23: 43200
B27: Víveres | C27: =SUM(C28:C33) -> 0
B35: Artículos y accesorios de cocina/limpieza | C35: =SUM(C36:C46) -> 0
B48: Mats. Para Mantto. De Cubiertas / Casco | C48: =SUM(C49:C53) -> 0
B55: Mats. Para Mantto. De Máquinas | C55: =SUM(C56:C63) -> 9757.93
A56: 45079 | B56: SA85937 / Switches de presión aceite para máquinas / Eliasib Birzayit Mendoza Luna | C56: 6374.03
A57: 45107 | B57: OC20230641 (624602) / Materiales para mantenimientos en máquinas | C57: 3383.9
B65: Mats. Mantto. Embarcaciones Menores | C65: =SUM(C66:C69) -> 8478
A66: 45083 | B66: SA85986 / Luces LED para remolque Rigel / María Teresa Reynoso Loera | C66: 8478
B71: Materiales para Mantenimiento en Dique Seco | C71: =SUM(C72) -> 0
B74: Equipo de seguridad y ayuda a la navegación | C74: =C75 -> 0
B77: Mats. para laboratorios y electrónico | C77: =SUM(C78) -> 0
B80: Otros | C80: =SUM(C81:C87) -> 77041.44
A81: 45091 | B81: OC20230568 (624602) / Termómetro para toma temperaturas a personal a bordo del BOAH | C81: 757
A82: 45104 | B82: TP82055 / Traspaso para cubrir costo de ropa trabajo personal DEO 2023 | C82: 76284.44
B90: SERVICIOS | C90: =C91+C97+C101+C104+C108+C112+C118+C122+C126+C129+C132+C135+C139+C147+C152+C162+C167+C204 -> 655400.38
B91: Mantenimiento a máquinas | C91: =SUM(C92:C95) -> 0
B97: Mantenimiento a cubiertas/casco | C97: =SUM(C98:C99) -> 0
B101: Mantenimiento en dique seco | C101: =SUM(C102) -> 0
B104: Mantenimiento a embarcaciones menores | C104: =SUM(C105:C106) -> 24667.2
A105: 45103 | B105: SA64535 (624602) / Elaboración de cálculo de arqueo Rigel / Uni Group Ingeniería y Ultrasonido, S. de R. L. de C. V. | C105: 7344
A106: 45106 | B106: OC20230633 (624602) / Mantenimiento muelles suspensión remolque Rigel | C106: 17323.2
B108: Mantenimiento a vehículos terrestres | C108: =SUM(C109:C110) -> 0
B112: Renta muelle | C112: =SUM(C113:C116) -> 107587.46
A113: 45097 | B113: SS64504 / Renta de muelle y electricidad BOAH mayo 2023 / Compañía Mexicana de Soluciones Onshore, S. de R. L. de C. V. | C113: 107587.46
B118: Personal por Outsourcing | C118: =SUM(C119:C120) -> 412899.5
A119: 45107 | B119: SS64582 (624602) / Pago de personal por Outsourcing junio 2023 / Arkadiarium, S. A. de C. V. | C119: 201205.49
A120: 45082 | B120: SS64394 (624602) / Pago de personal por Outsourcing mayo 2023 / Arkadiarium, S. A. de C. V. | C120: 211694.01
B122: Agenciamientos | C122: =SUM(C123:C124) -> 0
B126: Limpieza de ropa de cama | C126: =SUM(C127:C127) -> 0
B129: Seguridad y ayuda a la navegación | C129: =SUM(C130:C130) -> 4212
A130: 45107 | B130: SS64585 (624602) / Actualización de plano de seguridad BOAH / Uni Group Ingeniería y Ultrasonido, S. de R. L. de C. V. | C130: 4212
B132: Inspecciones ABS | C132: =C133 -> 0
B135: Mantenimiento a equipo científico y de laboratorio | C135: =SUM(C136:C137) -> 0
B139: Comunicaciones | C139: =SUM(C140:C145) -> 3044.65
A140: 45082 | B140: TP81574 / Cobro telefonía interna | C140: 28.67
A141: 45098 | B141: SS64510 (624602) / Repercusión INMARSAT BOAH Marzo 2023 / Financiera del Bienestar | C141: =55*17 -> 935
A142: 45098 | B142: SS64514 (624602) / Repercusión INMARSAT BOAH Abril 2023 / Financiera del Bienestar | C142: =55*17 -> 935
A143: 45085 | B143: TP81669 (624108) / Pago Telcel DEO Junio 2023 | C143: 1145.98
B147: Parque vehicular CICESE | C147: =SUM(C148:C150) -> 3300
A148: 45093 | B148: PV1053187 (624602) / Transportación personal DEO ENS-TIJ 20jun23 | C148: 1300
A149: 45093 | B149: PV1053186 (624602) / Transportación personal DEO ENS-TIJ 19jun23 | C149: 2000
B152: Comisiones/Servicios financieros/Pago de derechos | C152: =SUM(C153:C160) -> 435.4
A153: 45098 | B153: SS64511 (624602) / Porcentaje repercusión INMARSAT BOAH Marzo 2023 / Financiera del Bienestar | C153: 217.7
A154: 45098 | B154: SS64513 (624602) / Porcentaje repercusión INMARSAT BOAH Abril 2023 / Financiera del Bienestar | C154: 217.7
B162: Fletes diversos | C162: =SUM(C163:C165) -> 0
B167: Viáticos | C167: =SUM(C168:C202) -> 99254.17
A168: 28-Jun-23 | B168: SV11224 (624126) / Viáticos salida Rigel 30jun23 JCLV | C168: =299.2 -> 299.2
A169: 28-Jun-23 | B169: SV11223 (624126) / Viáticos salida Rigel 30jun23 ICN | C169: 300
A170: 28-Jun-23 | B170: SV11222 (624126) / Viáticos salida Rigel 29jun23 ICN | C170: 300
A171: 28-Jun-23 | B171: SV11221 (624126) / Viáticos salida Rigel 29jun23 JCLV | C171: 300
A172: 19-Jun-23 | B172: SV111129 (624126) / Viáticos prospección Eréndira 21jun23 ICN | C172: 503.3
A173: 19-Jun-23 | B173: SV111128 (624126) / Viáticos prospección Eréndira 21jun23 JCLV | C173: 513
A174: 19-Jun-23 | B174: SV111116 (624126) / Viáticos salida Rigel 20jun23 ICN | C174: 300
A175: 19-Jun-23 | B175: SV111115 (624126) / Viáticos salida Rigel 20jun23 JCLV | C175: 300
A176: 15-Jun-23 | B176: SV111044 (624108) / Marco Antonio Castillo Ramírez / Viáticos ENS-TUX 19jun23 | C176: 1105
A177: 15-Jun-23 | B177: SV111044 (624108) / Marco Antonio Castillo Ramírez / Boleto avión | C177: 8763
A178: 15-Jun-23 | B178: SV111043 (624108) / José Ramón López Chico / Viáticos ENS-TUX 19jun23 | C178: 1105
A179: 15-Jun-23 | B179: SV111043 (624108) / José Ramón López Chico / Boleto avión | C179: 8913
A180: 15-Jun-23 | B180: SV111042 (624108) / Julio Cesar Nuñez Zamudio / Viáticos ENS-TUX 19jun23 | C180: 1105
A181: 15-Jun-23 | B181: SV111042 (624108) / Julio Cesar Nuñez Zamudio / Boleto avión | C181: 8913
A182: 15-Jun-23 | B182: SV111041 (624108) / Rosario Félix Reyes / Viáticos ENS-TUX 19jun23 | C182: =379+592 -> 971
A183: 15-Jun-23 | B183: SV111041 (624108) / Rosario Félix Reyes / Boleto avión | C183: 7948
A184: 15-Jun-23 | B184: SV111040 (624108) / Carlos Enrique Ortiz de los Santos / Viáticos ENS-TUX 19jun23 | C184: 1105
A185: 15-Jun-23 | B185: SV111040 (624108) / Carlos Enrique Ortiz de los Santos / Boleto avión | C185: 7948
A186: 15-Jun-23 | B186: SV111039 (624108) / Pedro Nuñez Cota / Viáticos ENS-TUX 19jun23 | C186: 1685
A187: 15-Jun-23 | B187: SV111039 (624108) / Pedro Nuñez Cota / Boleto avión | C187: 7948
A188: 15-Jun-23 | B188: SV111038 (624108) / Gustavo Castro Navarro / Viáticos ENS-TUX 20jun23 | C188: 1229
A189: 15-Jun-23 | B189: SV111038 (624108) / Gustavo Castro Navarro / Boleto avión | C189: 6437
A190: 14-Jun-23 | B190: SV111130 (624602) / Erick Rafael Rivera Lemus / Renta automóvil en Tuxpan jun23 | C190: 13152.87
A191: 14-Jun-23 | B191: SV111030 (624108) / Erick Rafael Rivera Lemus / Viáticos MXL-TUX 18jun23 y estancia pre crucero | C191: =9024.6 -> 9024.6
A192: 14-Jun-23 | B192: SV111030 (624108) / Erick Rafael Rivera Lemus / Boleto avión | C192: 6437
A193: 28-Jun-23 | B193: SV111224 (624126) / Juan Carlos Leñero / Salida Rigel 30jun23 | C193: 299.2
A194: 28-Jun-23 | B194: SV111223 (624126) / Iván Castro Navarro / Salida Rigel 30jun23 | C194: 300
A195: 28-Jun-23 | B195: SV111222 (624126) / Iván Castro Navarro / Salida Rigel 29jun23 | C195: 300
A196: 28-Jun-23 | B196: SV111221 (624126) / Juan Carlos Leñero / Salida Rigel 29jun23 | C196: 300
A197: 30-Jun-23 | B197: OC20230636 (624602) / Maleta documentada adicional Erick Rivera | C197: 1450
B204: Otros | C204: =SUM(C205:C211) -> 0
B214: INVERSION | C214: =SUM(C215:C215) -> 0

Sheet JUL23
A2: JULIO 2023 | C2: =C4+C74 -> 184074.49
A3: Fecha | B3: Concepto | C3: Monto
B4: MATERIALES | C4: =C5+C10+C16+C21+C24+C31+C34+C40+C51+C57+C61+C65+C68 -> 42720.71
B5: Diesel para Buque | C5: =SUM(C6:C8) -> 0
B10: Gasolina para embarcaciones menores | C10: =SUM(C11:C14) -> 9476.46
A11: 45112 | B11: RFF11897 (624602) / Gasolina Rigel | C11: =1840.29+2380.07+2370.05+2886.05 -> 9476.46
B16: Gasolina para vehículos | C16: =SUM(C17:C19) -> 5125.04
A17: 45114 | B17: RFF11900 (624602) / Gasolina en Tuxpan | C17: =881.84 -> 881.84
A18: 45112 | B18: RFF11897 (624602) / Gasolina 15-C | C18: =900.03+225.01+800+1679.39+638.77 -> 4243.2
B21: Lubricantes | C21: =C22 -> 0
B24: Víveres | C24: =SUM(C25:C29) -> 1119
A25: 45114 | B25: RFF11900 (624602) / Agua para beber BOAH | C25: =132+180+450+132 -> 894
A26: 45112 | B26: RFF11897 (624602) / Agua para beber BOAH | C26: =225 -> 225
B31: Artículos y accesorios de cocina/limpieza | C31: =SUM(C32:C32) -> 1426.48
A32: 45118 | B32: OC20230681 (624602) / Materiales de limpieza para BOAH mayo 2023 | C32: =865.6+245+315.88 -> 1426.48
B34: Mats. Para Mantto. De Cubiertas / Casco | C34: =SUM(C35:C38) -> 17965.61
A35: 45114 | B35: RFF11900 (624602) / Aditivo antiburbuja para epóxico pisos BOAH | C35: =116 -> 116
A36: 45121 | B36: GRC103331 (624602) / Pintura para pisos BOAH | C36: =516.61+17333 -> 17849.61
B40: Mats. Para Mantto. De Máquinas | C40: =SUM(C41:C49) -> 7328.76
A41: 45121 | B41: GRC103331 (624602) / Tramo de armaflex | C41: 315
A42: 45117 | B42: OC20230675 (624602) / Materiales para mantenimientos máquinas BOAH | C42: 7013.76
B51: Mats. Mantto. Embarcaciones Menores | C51: =SUM(C52:C55) -> 279.36
A52: 45114 | B52: RFF11900 (624602) / Resortes para cuerpo aceleración Rigel | C52: 86.4
A53: 45112 | B53: RFF11897 (624602) / Tapón para cola de pato y llave para apriete cola pato Rigel | C53: =129+63.96 -> 192.96
B57: Materiales para Mantenimiento en Dique Seco | C57: =SUM(C58:C59) -> 0
B61: Equipo de seguridad y ayuda a la navegación | C61: =SUM(C62:C63) -> 0
B65: Mats. para laboratorios y electrónico | C65: =SUM(C66) -> 0
B68: Otros | C68: =SUM(C69:C71) -> 0
B74: SERVICIOS | C74: =C75+C80+C84+C88+C91+C94+C97+C100+C106+C110+C115+C118+C121+C128+C133+C143+C147+C175 -> 141353.78
B75: Mantenimiento a máquinas | C75: =SUM(C76:C78) -> 18676
A76: 45121 | B76: GRC103331 (624602) / Servicio de buceo para limpieza rejilla fondo BOAH | C76: 2320
A77: 45121 | B77: GRC103331 (624602) / Servicio de mantenimiento aires acondicionados | C77: 16356
B80: Mantenimiento a cubiertas/casco | C80: =SUM(C81:C82) -> 0
B84: Mantenimiento en dique seco | C84: =SUM(C85:C86) -> 0
B88: Mantenimiento a embarcaciones menores | C88: =C89 -> 0
B91: Mantenimiento a vehículos terrestres | C91: =SUM(C92) -> 0
B94: Renta muelle | C94: =C95 -> 0
B97: Personal por Outsourcing | C97: =C98 -> 0
B100: Agenciamientos | C100: =SUM(C101:C104) -> 11600
A101: 45121 | B101: GRC103331 (624602) / Agenciamientos TUX movimientos BOAH jun-jul23 | C101: =5800+5800 -> 11600
B106: Limpieza de ropa de cama | C106: =SUM(C107:C108) -> 5120
A107: 45121 | B107: GRC103331 (624602) / Lavandería de ropa de cama julio 2023 | C107: 3000
A108: 45118 | B108: OC20230681 (624602) / Lavandería de ropa cama BOAH mayo 2023 | C108: 2120
B110: Seguridad y ayuda a la navegación | C110: =SUM(C111:C113) -> 0
B115: Inspecciones ABS | C115: =SUM(C116) -> 0
B118: Mantenimiento a equipo científico y de laboratorio | C118: =C119 -> 0
B121: Comunicaciones | C121: =SUM(C122:C126) -> 2932.47
A122: 45114 | B122: RFF11900 / Envío documentos a CDMX para trámite licencia radio BOAH | C122: =851.49 -> 851.49
A123: 45138 | B123: SS64772 (624602) / Repercusión INMARSAT BOAH Mayo 2023 / Financiera del Bienestar | C123: =55*17 -> 935
A124: 45114 | B124: TP82282 (624108) / Pago Telcel DEO Julio 2023 | C124: 1145.98
B128: Parque vehicular CICESE | C128: =SUM(C129:C131) -> 2000
A129: 45121 | B129: PV1053280 (624602) / Transportación personal DEO TIJ-ENS 14jul23 | C129: 2000
B133: Comisiones/Servicios financieros/Pago de derechos | C133: =SUM(C134:C141) -> 13581.62
A134: 45114 | B134: RFF11900 (624602) / Pago derechos IFT licencia radio BOAH | C134: 1877
A135: 45112 | B135: RFF11897 (624602) / Pago derechos revisión cuadro obligaciones y plano seguridad BOAH | C135: =2524+2524 -> 5048
A136: 45138 | B136: SS64771 (624602) / Porcentaje repercusión INMARSAT BOAH Mayo 2023 / Financiera del Bienestar | C136: 217.92
A137: 45121 | B137: GRC103331 (624602) / Pago derechos examen psicofísico y expedición libreta mar ERRL | C137: =2039+611.7+532+532 -> 3714.7
A138: 45121 | B138: GRC103331 (624602) / Pago derechos SEMAR atraques y zarpes BOAH Jun-Jul23 | C138: =908+908+908 -> 2724
B143: Fletes diversos | C143: =SUM(C144:C145) -> 1451.42
A144: 45121 | B144: GRC103331 (624602) / Envío de CTD a Ensenada | C144: 1451.42
B147: Viáticos | C147: =SUM(C148:C173) -> 74296.02
A148: 11-Jul-23 | B148: SV111366 (624602) / Rosario Félix Reyes / TUX-ENS 14jul23 / Boleto avión | C148: 8168
A149: 11-Jul-23 | B149: SV111366 (624602) / Rosario Félix Reyes / TUX-ENS 14jul23 / Viáticos | C149: 1037.01
A150: 11-Jul-23 | B150: SV111365 (624602) / Carlos Enrique Ortiz de los Santos / TUX-ENS 14jul23 / Boleto avión | C150: 8009
A151: 11-Jul-23 | B151: SV111365 (624602) / Carlos Enrique Ortiz de los Santos / TUX-ENS 14jul23 / Viáticos | C151: 1105
A152: 11-Jul-23 | B152: SV111364 (624602) / Pedro Nuñez Cota / TUX-ENS 14jul23 / Boleto avión | C152: 8009
A153: 11-Jul-23 | B153: SV111364 (624602) / Pedro Nuñez Cota / TUX-ENS 14jul23 / Viáticos | C153: 1285
A154: 11-Jul-23 | B154: SV111363 (624602) / Marco Antonio Castillo Ramírez / TUX-ENS 14jul23 / Boleto avión | C154: 7776
A155: 11-Jul-23 | B155: SV111363 (624602) / Marco Antonio Castillo Ramírez / TUX-ENS 14jul23 / Viáticos | C155: 912.01
A156: 11-Jul-23 | B156: SV111362 (624602) / José Ramón López Chico / TUX-ENS 14jul23 / Boleto avión | C156: 7776
A157: 11-Jul-23 | B157: SV111362 (624602) / José Ramón López Chico / TUX-ENS 14jul23 / Viáticos | C157: 1174
A158: 11-Jul-23 | B158: SV111361 (624602) / Julio Cesar Nuñez Zamudio / TUX-ENS 14jul23 / Boleto avión | C158: 7776
A159: 11-Jul-23 | B159: SV111361 (624602) / Julio Cesar Nuñez Zamudio / TUX-ENS 14jul23 / Viáticos | C159: 1105
... A163: 4-Jul-23 | B163: SV111256 (624602) / Erick Rafael Rivera Lemus / TUX-ENS 07jul23 / Viáticos | C163: 1522
B175: Otros | C175: =SUM(C176:C179) -> 11696.25
A176: 45114 | B176: RFF11900 (624602) / Recolección de basura BOAH Julio 2023 | C176: =1160+1740+1740 -> 4640
A177: 45112 | B177: RFF11897 (624602) / Renta slip Rigel en marina Coral | C177: =2126.25 -> 2126.25
A178: 45121 | B178: GRC103331 (624602) / Pago derechos cursos para libreta mar ERRL | C178: 4930
B182: INVERSION | C182: =SUM(C183:C183) -> 0

Sheet AGO23
A2: AGOSTO 2023 | C2: =C4+C97 -> 712948.8
A3: Fecha | B3: Concepto | C3: Monto
B4: MATERIALES | C4: =C5+C9+C15+C20+C26+C36+C44+C53+C64+C71+C80+C85+C89 -> 95058.69
B5: Diesel para Buque
B9: Gasolina para embarcaciones menores | C9: =SUM(C10:C13) -> 0
B15: Gasolina para vehículos | C15: =SUM(C16:C18) -> 750.1
A16: 31-Ago-23 | B16: RFF11963 (624602) / Gasolina vehículos TUX | C16: =750.1 -> 750.1
B20: Lubricantes | C20: =SUM(C21:C24) -> 0
B26: Víveres | C26: =SUM(C27:C34) -> 59039.33
A27: 7-Ago-23 | B27: GRC103332 (624602) / Víveres cruceros RecupBOC y Canek | C27: 59039.33
B36: Artículos y accesorios de cocina/limpieza | C36: =SUM(C37:C42) -> 6134.4
A37: 31-Ago-23 | B37: RFF11963 (624602) / Bolsas basura, mats limpieza TUX, desengrasante, toallas amarillas | C37: =4261.64+1127.5+367.26+208+170 -> 6134.4
B44: Mats. Para Mantto. De Cubiertas / Casco | C44: =SUM(C45:C51) -> 11226.41
A45: 9-Ago-23 | B45: SA86438 (624602) / Fundas Nicopress diferentes tamaños para BOAH / Eliasib Birzayit Mendoza Luna | C45: 11226.41
B53: Mats. Para Mantto. De Máquinas | C53: =SUM(C54:C62) -> 2950
A54: 31-Ago-23 | B54: RFF11963 (624602) / Gas R22 | C54: =2950 -> 2950
B64: Mats. Mantto. Embarcaciones Menores | C64: =SUM(C65:C69) -> 1645
A65: 31-Ago-23 | B65: RFF11963 (624602) / Cable extensión transductor nuevo ecosonda Rigel, adhesivo epóxico | C65: =1500+145 -> 1645
B71: Materiales para Mantenimiento en Dique Seco | C71: =SUM(C72:C78) -> 0
B80: Equipo de seguridad y ayuda a la navegación | C80: =SUM(C81:C83) -> 12287.92
A81: 7-Ago-23 | B81: SA86396 (624602) / 4 Luces LED para aros salvavidas ACR 3947 SM-3 / Agencia Arjona, S. A. de C. V. | C81: 12287.92
B85: Mats. para laboratorios y electrónico | C85: =SUM(C86:C87) -> 0
B89: Otros | C89: =SUM(C90:C94) -> 1025.53
A90: 31-Ago-23 | B90: RFF11963 (624602) / Papelería, lentes y guantes carnaza, solera | C90: =209.1+490.14+326.29 -> 1025.53
B97: SERVICIOS | C97: =C98+C105+C111+C114+C118+C121+C124+C127+C132+C136+C140+C143+C147+C155+C161+C169+C172+C200 -> 617890.11
B98: Mantenimiento a máquinas | C98: =SUM(C99:C103) -> 0
B105: Mantenimiento a cubiertas/casco | C105: =SUM(C106:C109) -> 0
B111: Mantenimiento en dique seco | C111: =SUM(C112) -> 0
B114: Mantenimiento a embarcaciones menores | C114: =SUM(C115:C116) -> 696
A115: 14-Ago-23 | B115: SS64898 (624602) / Recarga de extintores Rigel 2023 / SOS Balsas y extintores de Baja California, S. A. de C. V. | C115: 696
B118: Mantenimiento a vehículos terrestres | C118: =SUM(C119) -> 0
B121: Renta muelle | C121: =C122 -> 232481.66
A122: 15-Ago-23 | B122: SS64907 (624602) / Renta de muelle y electricidad junio 2023 / Compañía Mexicana de Soluciones Onshore, S. de R. L. de C. V. | C122: 232481.66
B124: Personal por Outsourcing | C124: =C125 -> 201205.48
A125: 7-Ago-23 | B125: SS64835 (624602) / Pago de personal por Outsourcing julio 2023 / Arkadiarium, S. A. de C. V. | C125: 201205.48
B127: Agenciamientos | C127: =SUM(C128:C130) -> 0
B132: Limpieza de ropa de cama | C132: =SUM(C133:C134) -> 0
B136: Seguridad y ayuda a la navegación | C136: =SUM(C137:C138) -> 0
B140: Inspecciones ABS | C140: 0
B143: Mantenimiento a equipo científico y de laboratorio | C143: =SUM(C144:C145) -> 0
B147: Comunicaciones | C147: =SUM(C148:C153) -> 28361.57
A148: 17-Ago-23 | B148: SS64916 (624602) / Servicio de Internet Stalink 400Gb para crucero Canek 28 / Eliasib Birzayit Mendoza Luna | C148: 24641.28
A149: 22-Ago-23 | B149: SS64946 / Repercusión INMARSAT BOAH Junio 2023 / Financiera del Bienestar | C149: =55*17 -> 935
A150: 22-Ago-23 | B150: SS64950 / Repercusión INMARSAT BOAH Julio 2023 / Financiera del Bienestar | C150: =55*17 -> 935
A151: 31-Ago-23 | B151: RFF11963 (624602) / Envío documentos a Tuxpan | C151: =704.31 -> 704.31
A152: 11-Ago-23 | B152: TP82818 (624108) / Pago Telcel DEO Agosto 2023 | C152: 1145.98
B155: Parque vehicular CICESE | C155: =SUM(C156:C159) -> 3381.5
A156: 31-Ago-23 | B156: PV1053408 (624108) / Transportación personal DEO TIJ-ENS 01sep23 | C156: 1481.5
A157: 24-Ago-23 | B157: PV1053374 (624108) / Transportación personal DEO TIJ-ENS 25ago23 | C157: 400
A158: 14-Ago-23 | B158: PV1053346 (624602) / Transportación personal DEO ENS-TIJ 16ago23 | C158: 1500
B161: Comisiones/Servicios financieros/Pago de derechos | C161: =SUM(C162:C167) -> 14833.87
A162: 14-Ago-23 | B162: SS64896 (624602) / Pago derechos exportación temporal CTD DEO / Agencia Aduanal Pérez Ortiz, S. C. | C162: 2473.2
A163: 22-Ago-23 | B163: SS64945 / Porcentaje repercusión INMARSAT BOAH Junio 2023 / Financiera del Bienestar | C163: 214.18
A164: 22-Ago-23 | B164: SS64947 / Porcentaje repercusión INMARSAT BOAH Julio 2023 / Financiera del Bienestar | C164: 218.49
A165: 14-Ago-23 | B165: OC20230779 (624602) / Sanidad, agenciamiento y derechos SEMAR atraque BOAH TUX post InstBOC | C165: 11928
B169: Fletes diversos | C169: =SUM(C170) -> 11628.68
A170: 18-Ago-23 | B170: SS64929 (624602) / Pago envío CTD de San Diego a Bellevue / Miramar Customs Brokers, Inc. | C170: =684.04*17 -> 11628.68
B172: Viáticos | C172: =SUM(C173:C198) -> 121473.35
A173: 15-Ago-23 | B173: SV111547 (624602) / Julio Cesar Nuñez Zamudio / ENS-TUX 16ago23 / Viáticos | C173: =592+513 -> 1105
A174: 15-Ago-23 | B174: SV111547 (624602) / Julio Cesar Nuñez Zamudio / ENS-TUX 16ago23 / Boleto avión | C174: 6725
A175: 14-Ago-23 | B175: SV111533 (624602) / Rosario Félix Reyes / ENS-TUX 16ago23 / Boleto avión | C175: 5975
A176: 14-Ago-23 | B176: SV111533 (624602) / Rosario Félix Reyes / ENS-TUX 16ago23 / Viáticos | C176: 1105
A177: 14-Ago-23 | B177: SV111531 (624602) / Marco Antonio Castillo Ramírez / ENS-TUX 16ago23 / Boleto avión | C177: 6725
A178: 14-Ago-23 | B178: SV111531 (624602) / Marco Antonio Castillo Ramírez / ENS-TUX 16ago23 / Viáticos | C178: 1105
A179: 14-Ago-23 | B179: SV111530 (624602) / Carlos Enrique Ortiz de los Santos / ENS-TUX 16ago23 / Boleto avión | C179: 5975
A180: 14-Ago-23 | B180: SV111530 (624602) / Carlos Enrique Ortiz de los Santos / ENS-TUX 16ago23 / Viáticos | C180: 1102.01
A181: 14-Ago-23 | B181: SV111529 (624602) / Pedro Nuñez Cota / ENS-TUX 16ago23 / Boleto avión | C181: 5975
A182: 14-Ago-23 | B182: SV111529 (624602) / Pedro Nuñez Cota / ENS-TUX 16ago23 / Viáticos | C182: 1105
A183: 14-Ago-23 | B183: SV111525 (624602) / Gustavo Castro Navarro / ENS-TUX 16ago23 / Boleto avión | C183: 5975
A184: 14-Ago-23 | B184: SV111525 (624602) / Gustavo Castro Navarro / ENS-TUX 16ago23 / Viáticos | C184: 1105
A185: 11-Ago-23 | B185: SV111520 (624602) / Juan Carlos Leñero / ENS-TUX-ENS 16-25ago23 / Boleto avión ida | C185: 6725
... A195: 29-Ago-23 | B195: SV111724 (624108) / Marco Antonio Castillo Ramírez / TUX-ENS 01sep23 / Viáticos | C195: 1105
B200: Otros | C200: =SUM(C201:C206) -> 3828
A201: 31-Ago-23 | B201: RFF11963 (624602) / Suministro de agua en pipa TUX ago23, recolección basura | C201: =1508+2320 -> 3828
B209: INVERSION | C209: =SUM(C210:C210) -> 0

Sheet SEP23
A2: SEPTIEMBRE 2023 | C2: =C4+C87 -> 1077114.6
A3: Fecha | B3: Concepto | C3: Monto
B4: MATERIALES | C4: =C5+C9+C15+C21+C25+C32+C39+C48+C57+C64+C69+C76+C79 -> 173717.9
B5: Diesel para Buque | C5: =SUM(C6:C7) -> 0
B9: Gasolina para embarcaciones menores | C9: =SUM(C10:C13) -> 2400
A10: 45175 | B10: RFF11969 / Gasolina para Rigel | C10: =2400 -> 2400
B15: Gasolina para vehículos | C15: =SUM(C16:C19) -> 1572.2
A16: 45175 | B16: RFF11969 / Gasolina 15-C | C16: =1572.2 -> 1572.2
B21: Lubricantes | C21: =SUM(C22:C23) -> 0
B25: Víveres | C25: =SUM(C26:C30) -> 63719.8
A26: 45175 | B26: RFF11969 / Garrafones de agua para buque | C26: =90+150 -> 240
A27: 45173 | B27: OC20230876 (624602) / Vitualla en Tuxpan | C27: 3645
A28: 45173 | B28: GRC103401 (624602) / Vitualla en Tuxpan | C28: =8065.28+12969.11+12612.3+5097.11+4910+1823+14358 -> 59834.8
B32: Artículos y accesorios de cocina/limpieza | C32: =SUM(C33:C37) -> 1841.04
A33: 45175 | B33: RFF11969 / Bolsas para basura | C33: =909.43+150.01 -> 1059.44
A34: 45183 | B34: RFF11979 / Filtros cafetera, servilletas | C34: =781.6 -> 781.6
B39: Mats. Para Mantto. De Cubiertas / Casco | C39: =SUM(C40:C46) -> 12456.5
A40: 45175 | B40: RFF11969 / Removedor de pintura Comex | C40: =2819 -> 2819
A41: 45183 | B41: RFF11979 / Rodillo y zapatos pico | C41: =1594 -> 1594
A42: 45181 | B42: GRC103397 (624602) / Materiales para pintado pisos interior BOAH | C42: =8043.5 -> 8043.5
B48: Mats. Para Mantto. De Máquinas | C48: =SUM(C49:C55) -> 18992.82
A49: 45175 | B49: RFF11969 / 3 Tambores de plástico para recolección de aceite residual, trapos, codo acero | C49: =3119.99+1125+283.52 -> 4528.51
A50: 45183 | B50: RFF11979 / Tambores de plástico, sellos cónicos, careta soldar, electrodos | C50: =2080+34.56+833.22+62.38 -> 3010.16
A51: 45176 | B51: SA86731 (624602) / Sensor magnético para tacómetro motogen BOAH / Eliasib Birzayit Mendoza Luna | C51: 8654.15
A52: 45195 | B52: RFF12006 (624602) / Baterías DeWalt para máquinas | C52: =2800 -> 2800
B57: Mats. Mantto. Embarcaciones Menores | C57: =SUM(C58:C62) -> 22166.376
A58: 45183 | B58: RFF11979 (624602) / Materiales para mantenimiento remolque Rigel | C58: =2162.7+4353.9+308.1 -> 6824.7
A59: 45195 | B59: RFF12006 (624602) / Material acero para remolque BOAH, caja herramientas, acero | C59: =1949.24+1088+323.51 -> 3360.75
A60: 45198 | B60: SA87008 (624602) / Bomba de agua Volvo Penta para motor Rigel / Agencia Arjona, S. A. de C. V. | C60: =685.8*17.47 -> 11980.926
B64: Materiales para mantenimiento en dique seco | C64: =SUM(C65:C67) -> 0
B69: Equipo de seguridad y ayuda a la navegación | C69: =SUM(C70:C74) -> 44296.216
A70: 45183 | B70: RFF11979 / Liberador hidrostático para EPIRB BOAH | C70: =3652.81 -> 3652.81
A71: 45182 | B71: SA86754 (624602) / Bengalas para BOAH / Servicios Múltiples del Sureste, S. A. de C. V. | C71: =1127.52*17.55 -> 19787.976
A72: 45177 | B72: SA86745 (624602) / 8 aros salvavidas Jim Buoy para BOAH / Agencia Arjona, S. A. de C. V. | C72: 15605.34
A73: 45177 | B73: SA86740 (624602) / 3 chalecos salvavidas para operaciones Rigel / Agencia Arjona, S. A. de C. V. | C73: 5250.09
B76: Mats. para laboratorios y electrónico | C76: =C77 -> 0
B79: Otros | C79: =SUM(C80:C84) -> 6272.95
A80: 45175 | B80: RFF11969 / Agua en pipa para BOAH, electrodos | C80: =1508+132.21+190.87 -> 1831.08
A81: 45183 | B81: RFF11979 / Materiales para preparativos Noche de las Ciencias | C81: =115.6+197.6+1328+245.9 -> 1887.1
A82: 45195 | B82: RFF12006 (624602) / Materiales para preparativos Noche de las Ciencias | C82: =895+240+427.99+89.42+565+88.36+249 -> 2554.77
B87: SERVICIOS | C87: =C88+C95+C100+C103+C106+C109+C115+C118+C122+C128+C133+C136+C139+C149+C155+C164+C170+C201 -> 903396.7
B88: Mantenimiento a máquinas | C88: =SUM(C89:C93) -> 0
B95: Mantenimiento a cubiertas/casco | C95: =SUM(C96:C98) -> 0
B100: Mantenimiento en dique seco | C100: =SUM(C101) -> 0
B103: Mantenimiento a embarcaciones menores | C103: =C104 -> 0
B106: Mantenimiento a vehículos terrestres | C106: =SUM(C107) -> 0
B109: Renta muelle | C109: =SUM(C110:C113) -> 422036.29
A110: 45196 | B110: SS65254 (624602) / Renta de muelle y energía eléctrica BOAH agosto 2023 / Compañía Mexicana de Soluciones Onshore, S. de R. L. de C. V. | C110: 276554.51
A111: 45196 | B111: SS65253 (624602) / Renta de muelle y energía eléctrica BOAH 15 a 31 julio 2023 / Compañía Mexicana de Soluciones Onshore, S. de R. L. de C. V. | C111: 145481.78
B115: Personal por Outsourcing | C115: =C116 -> 201205.5
A116: 45180 | B116: SS65107 (624602) / Personal outsourcing agosto 2023 / Arkadiarium, S. A. de C. V. | C116: 201205.5
B118: Agenciamientos | C118: =SUM(C119:C120) -> 17400
A119: 45181 | B119: GRC103397 (624602) / Agenciamiento BOAH Tuxpan | C119: =5800+5800+5800 -> 17400
B122: Limpieza de ropa de cama | C122: =SUM(C123:C126) -> 0
B128: Seguridad y ayuda a la navegación | C128: =SUM(C129:C131) -> 24635.9
A129: 45197 | B129: SS65272 (624602) / Elaboración de tablilla desvíos BOAH / José de Jesús Mejía Páramo | C129: 5400
A130: 45197 | B130: SS65269 (624602) / Mantenimiento de SART Pathfinder3 BOAH / Eliasib Birzayit Mendoza Luna | C130: 19235.9
B133: Inspecciones ABS | C133: =C134 -> 0
B136: Mantenimiento a equipo científico y de laboratorio | C136: =C137 -> 0
B139: Comunicaciones | C139: =SUM(C140:C147) -> 2565.95
A140: 45183 | B140: RFF11979 / Envío oficio a IFT | C140: 429.97
A141: 45195 | B141: SS65247 (624602) / Repercusión INMARSAT BOAH Agosto 2023 / Financiera del Bienestar | C141: =55*18 -> 990
A142: 45183 | B142: TP83626 (624108) / Pago Telcel DEO Septiembre 2023 | C142: 1145.98
B149: Parque vehicular CICESE | C149: =SUM(C150:C153) -> 5844.78
A150: 45198 | B150: PV1053581 (624602) / Transportación personal DEO TIJ-ENS 29sep23 | C150: 800
A151: 45189 | B151: PV1053529 (624602) / Transportación personal DEO ENS-TIJ 25sep23 | C151: 1450.36
A152: 45189 | B152: PV1053528 (624602) / Transportación personal DEO ENS-TIJ 20sep23 | C152: 1300
A153: 45198 | B153: PV1053583 (624602) / Transportación personal DEO TIJ-ENS 06oct23 | C153: 2294.42
B155: Comisiones/Servicios financieros/Pago de derechos | C155: =SUM(C156:C162) -> 31126.37
A156: 45189 | B156: SS65194 (624602) / Servicio por reexpedición de pedimento aceites para motogens para envío a TUX / Rudametkin Distribuidora, S. A. de C. V. | C156: 4485.24
A157: 45195 | B157: RFF12006 (624602) / Pago derechos zarpe y atraque salida Rigel apoyo evento natación | C157: =368+368 -> 736
A158: 45181 | B158: GRC103397 (624602) / Pagos derechos BOAH Tuxpan crucero agosto 2023 e inspección | C158: =908+1816+908+9521 -> 13153
A159: 45195 | B159: SS65246 (624602) / Porcentaje repercusión INMARSAT BOAH Agosto 2023 / Financiera del Bienestar | C159: 219.05
A160: 45191 | B160: SS65229 (624602) / Permiso SEDENA transportación bengalas BOAH / Servicios Múltiples del Sureste, S. A. de C. V. | C160: =505.76*18 -> 9103.68
A161: 45190 | B161: OC20230990 (624602) / Pago impuestos aduana equipo seguridad BOAH para envío a Tuxpan | C161: 3429.4
B164: Fletes diversos | C164: =SUM(C165:C168) -> 15875.35
A165: 45181 | B165: GRC103397 (624602) / Flete de materiales a Tuxpan | C165: 7899.09
A166: 45190 | B166: OC20230989 (624602) / Envío de material de seguridad del BOAH a Tuxpan | C166: 7976.26
B170: Viáticos | C170: =SUM(C171:C199) -> 179578.56
A171: 20-Sep-23 | B171: SV112085 (624602) / Ernesto Alonso Valenzuela Palacios / ENS-TUX-ENS 25-29sep23 / Boleto avión | C171: =14117 -> 14117
A172: 20-Sep-23 | B172: SV112085 (624602) / Ernesto Alonso Valenzuela Palacios / ENS-TUX-ENS 25-29sep23 / Viáticos | C172: 6105
A173: 1-Sep-23 | B173: SV111768 (624108) / Pedro Nuñez Cota / TUX-ENS 01sep23 / Boleto avión | C173: 7708
A174: 1-Sep-23 | B174: SV111768 (624108) / Pedro Nuñez Cota / TUX-ENS 01sep23 / Viáticos | C174: =592+513 -> 1105
A175: 1-Sep-23 | B175: SV111770 (624108) / Carlos Enrique Ortiz de los Santos / TUX-ENS 01sep23 / Boleto avión | C175: 7708
A176: 1-Sep-23 | B176: SV111770 (624108) / Carlos Enrique Ortiz de los Santos / TUX-ENS 01sep23 / Viáticos | C176: =592+723.51 -> 1315.51
A177: 1-Sep-23 | B177: SV111771 (624108) / Rosario Félix Reyes / TUX-ENS 01sep23 / Boleto avión | C177: 7708
A178: 1-Sep-23 | B178: SV111771 (624108) / Rosario Félix Reyes / TUX-ENS 01sep23 / Viáticos | C178: 1104
A179: 1-Sep-23 | B179: SV111772 (624108) / Gustavo Castro Navarro / TUX-ENS 01sep23 / Boleto avión | C179: 7708
A180: 1-Sep-23 | B180: SV111772 (624108) / Gustavo Castro Navarro / TUX-ENS 01sep23 / Viáticos | C180: 1105
A181: 1-Sep-23 | B181: SV111773 (624108) / Julio César Nuñez Zamudio / TUX-ENS 01sep23 / Boleto avión | C181: 8858
A182: 1-Sep-23 | B182: SV111773 (624108) / Julio César Nuñez Zamudio / TUX-ENS 01sep23 / Viáticos | C182: 1105
A183: 4-Sep-23 | B183: SV111782 (624108) / Juan Carlos Leñero / Salida Rigel 05sep23 | C183: 300
A184: 15-Sep-23 | B184: SV112035 (624602) / Erick Rafael Rivera Lemus / ENS-TUX-ENS 20-29sep23 / Boleto avión | C184: 15333
A185: 15-Sep-23 | B185: SV112035 (624602) / Erick Rafael Rivera Lemus / ENS-TUX-ENS 20-29sep23 / Viáticos | C185: 38725.12
A186: 19-Sep-23 | B186: SV112067 (624602) / Pedro Nuñez Cota / ENS-TUX-ENS 25sep-06oct23 / Boleto avión | C186: 11872
A187: 19-Sep-23 | B187: SV112067 (624602) / Pedro Nuñez Cota / ENS-TUX-ENS 25sep-06oct23 / Viáticos | C187: =1624+967 -> 2591
A188: 19-Sep-23 | B188: SV112074 (624602) / Carlos Enrique Ortiz de los Santos / ENS-TUX-ENS 25sep-06oct23 / Boleto avión | C188: 11872
A189: 19-Sep-23 | B189: SV112074 (624602) / Carlos Enrique Ortiz de los Santos / ENS-TUX-ENS 25sep-06oct23 / Viáticos | C189: 2650
A190: 19-Sep-23 | B190: SV112075 (624602) / Julio César Nuñez Zamudio / ENS-TUX-ENS 25sep-06oct23 / Boleto avión | C190: 13372
A191: 19-Sep-23 | B191: SV112075 (624602) / Julio César Nuñez Zamudio / ENS-TUX-ENS 25sep-06oct23 / Viáticos | C191: =1184+1026 -> 2210
...

Sheet OCT23
A2: OCTUBRE 2023 | C2: =C4+C94 -> 3105954.8
A3: Fecha | B3: Concepto | C3: Monto
B4: MATERIALES | C4: =C5+C9+C16+C22+C25+C36+C42+C51+C62+C68+C73+C77+C82 -> 308434.76
B5: Diesel para Buque | C5: =SUM(C6:C7) -> 0
B9: Gasolina para embarcaciones menores | C9: =SUM(C10:C14) -> 2400
A10: 45218 | B10: RFF12060 (624602) / Gasolina Rigel | C10: 2400
B16: Gasolina para vehículos | C16: =SUM(C17:C20) -> 4406.53
A17: 45205 | B17: RFF12025 (624602) / Gasolina para 15-C | C17: 1579.96
A18: 45218 | B18: RFF12060 (624602) / Gasolina para 15-C | C18: =1626.47+1200.1 -> 2826.57
B22: Lubricantes | C22: =C23 -> 0
B25: Víveres | C25: =SUM(C26:C34) -> 91953.74
A26: 45205 | B26: RFF12025 (624602) / Garrafones agua BOAH | C26: 150
A27: 45203 | B27: GRC103457 (624602) / Avituallamiento víveres BOAH estancia TUX | C27: =352.2+500.19+6755.43+2647.2+1525+6684.4+154.78+307.25 -> 18926.45
A28: 45230 | B28: GRC103604 (624602) / Avituallamiento víveres BOAH estancia TUX oct23 | C28: 72877.29
B36: Artículos y accesorios de cocina/limpieza | C36: =SUM(C37:C40) -> 559
A37: 45218 | B37: RFF12060 (624602) / Materiales limpieza BOAH | C37: 559
B42: Mats. Para Mantto. De Cubiertas / Casco | C42: =SUM(C43:C49) -> 0
B51: Mats. Para Mantto. De Máquinas | C51: =SUM(C52:C60) -> 192458.01
A52: 45210 | B52: SA87447 (624602) / Bomba de alta presión CAT para desaladora BOAH / Eliasib Birzayit Mendoza Luna | C52: 189000.93
A53: 45218 | B53: RFF12060 (624602) / Válvula reguladora refri verduras BOAH, Spud mingitorio | C53: =3417.08+40 -> 3457.08
B62: Mats. Mantto. Embarcaciones Menores | C62: =SUM(C63:C65) -> 11342.05
A63: 45205 | B63: RFF12025 (624602) / Acero PTR y solera, tornillería, tape azul y rodillos, removedor óxido, adhesivo | C63: =2117.14+1282.39+795+539.88+378 -> 5112.41
A64: 45218 | B64: RFF12060 (624602) / Materiales mantenimiento remolque Rigel | C64: =396+1324+1713.8+1102.89+211.05+1271+210.9 -> 6229.64
B68: Materiales para Mantenimiento en Dique Seco | C68: =SUM(C69:C71) -> 0
B73: Equipo de seguridad y ayuda a la navegación | C73: =C75 -> 0
B77: Mats. para laboratorios y electrónico | C77: =SUM(C78:C80) -> 0
B82: Otros | C82: =SUM(C83:C91) -> 5315.43
A83: 45205 | B83: RFF12025 (624602) / Resina impresora 3d tecnomecánica, batería cámara DEO, caja cartón | C83: =3828+500+240 -> 4568
A84: 45218 | B84: RFF12060 (624602) / Materiales para viaje a BLA Dra. Elena Solana | C84: =747.43 -> 747.43
B94: SERVICIOS | C94: =C95+C102+C112+C115+C121+C124+C132+C139+C145+C150+C158+C161+C165+C174+C185+C197+C200+C255 -> 2797520
B95: Mantenimiento a máquinas | C95: =SUM(C96:C100) -> 299980
A96: 45205 | B96: RFF12025 (624602) / Reparación tanque separador aguas oleosas | C96: =4640 -> 4640
A97: 45218 | B97: SS65725 (624602) / Reparación de marco A popa y grúa BOAH / Ruvaships, S. A. de C. V. | C97: 288840
A98: 45218 | B98: GRC103641 (624602) / Cambio válvula evaporador refri verduras BOAH | C98: 6500
B102: Mantenimiento a cubiertas/casco | C102: =SUM(C103:C110) -> 0
B112: Mantenimiento en dique seco | C112: =SUM(C113) -> 0
B115: Mantenimiento a embarcaciones menores | C115: =SUM(C116:C119) -> 1890
A116: 45205 | B116: RFF12025 (624602) / Reparación bombas agua Rigel | C116: =1890 -> 1890
B121: Mantenimiento a vehículos terrestres | C121: =SUM(C122) -> 0
B124: Renta muelle | C124: =SUM(C125:C130) -> 1202787.5
A125: 45208 | B125: SS65952 (624602) / Estadía en muelle y energía eléctrica BOAH Diciembre 2023 / Compañía Mexicana de Soluciones Onshore, S. de R. L. de C. V. | C125: 276362.16
A126: 45208 | B126: SS65951 (624602) / Estadía en muelle y energía eléctrica BOAH Noviembre 2023 / Compañía Mexicana de Soluciones Onshore, S. de R. L. de C. V. | C126: 269407.96
A127: 45208 | B127: SS65950 (624602) / Estadía en muelle y energía eléctrica BOAH Octubre 2023 / Compañía Mexicana de Soluciones Onshore, S. de R. L. de C. V. | C127: 276362.16
A128: 45208 | B128: SS65929 (624602) / Estadía en muelle y energía eléctrica BOAH, 2 a 14 de julio 2023 / Compañía Mexicana de Soluciones Onshore, S. de R. L. de C. V. | C128: 111247.23
A129: 45208 | B129: SS65949 (624602) / Estadía en muelle y energía eléctrica BOAH Septiembre 2023 / Compañía Mexicana de Soluciones Onshore, S. de R. L. de C. V. | C129: 269407.95
B132: Personal por Outsourcing | C132: =SUM(C133:C137) -> 804821.95
A133: 45208 | B133: SS65922 (624602) / Tripulación outsourcing BOAH noviembre 2023 / Arkadiarium, S. A. de C. V. | C133: 201205.48
A134: 45208 | B134: SS65916 (624602) / Tripulación outsourcing BOAH octubre 2023 / Arkadiarium, S. A. de C. V. | C134: 201205.48
A135: 45204 | B135: SS65532 (624602) / Tripulación outsourcing BOAH septiembre 2023 / Arkadiarium, S. A. de C. V. | C135: 201205.51
A136: 45208 | B136: SS65925 (624602) / Tripulación outsourcing BOAH diciembre 2023 / Arkadiarium, S. A. de C. V. | C136: 201205.48
B139: Agenciamientos | C139: =SUM(C140:C143) -> 0
B145: Limpieza de ropa de cama | C145: =SUM(C146:C148) -> 2629
A146: 45218 | B146: GRC103641 (624602) / Lavado ropa cama BOAH Oct23 | C146: 2629
B150: Seguridad y ayuda a la navegación | C150: =SUM(C151:C156) -> 215294.18
A151: 45205 | B151: RFF12025 (624602) / Rellenado tanques aire comprimido equipo SCBA BOAH | C151: 348
A152: 45205 | B152: SS65701 (624602) / Mantenimiento anual 2023 de balsas, extintores y sistemas fijos contra incendio BOAH / Servicios Múltiples del Sureste, S. A. de C. V. | C152: =11784.33*18.24 -> 214946.18
B158: Inspecciones ABS | C158: =C159 -> 0
B161: Mantenimiento a equipo científico y de laboratorio | C161: =SUM(C162:C163) -> 0
B165: Comunicaciones | C165: =SUM(C166:C172) -> 6886.38
A166: 45205 | B166: RFF12025 (624602) / Envío aros salvavidas a BOAH Tuxpan | C166: 3916.38
A167: 45208 | B167: SS65961 (624602) / Repercusión INMARSAT BOAH Noviembre 2023 / Financiera del Bienestar | C167: =55*18 -> 990
A168: 45208 | B168: SS65960 (624602) / Repercusión INMARSAT BOAH Octubre 2023 / Financiera del Bienestar | C168: =55*18 -> 990
A169: 45208 | B169: SS65959 (624602) / Repercusión INMARSAT BOAH Septiembre 2023 / Financiera del Bienestar | C169: =55*18 -> 990
B174: Parque vehicular CICESE | C174: =SUM(C175:C183) -> 8546.33
A175: 45208 | B175: PV1053761 (624602) / Transportación personal DEO TIJ-ENS 14oct23 | C175: 1742
A176: 45208 | B176: PV1053758 (624602) / Transportación personal DEO ENS-TIJ 11oct23 | C176: 804.33
A177: 45205 | B177: PV1053717 (624602) / Transportación personal DEO TIJ-ENS 10nov23 | C177: 2000
A178: 45205 | B178: PV1053714 (624602) / Transportación personal DEO TIJ-ENS 31oct23 | C178: 2000
A179: 45205 | B179: PV1053712 (624602) / Transportación personal DEO ENS-TIJ 23oct23 | C179: 2000
B185: Comisiones/Servicios financieros/Pago de derechos | C185: =SUM(C186:C195) -> 10828.7
A186: 45208 | B186: GRC103472 (624602) / Pago derechos publicación DOF licitación diesel BOAH | C186: =10048 -> 10048
A187: 45208 | B187: SS65958 (624602) / Porcentaje repercusión INMARSAT BOAH Noviembre 2023 / Financiera del Bienestar | C187: 219.05
A188: 45208 | B188: SS65956 (624602) / Porcentaje repercusión INMARSAT BOAH Octubre 2023 / Financiera del Bienestar | C188: 219.6
A189: 45208 | B189: SS65955 (624602) / Porcentaje repercusión INMARSAT BOAH Octubre 2023 / Financiera del Bienestar | C189: 219.05
A190: 45218 | B190: RFF12060 (624602) / Derechos por revisión pliego observaciones Rigel | C190: 123
B197: Fletes diversos | C197: =SUM(C198) -> 22043.48
A198: 45205 | B198: SS65650 (624602) / Recolección y disposición final de aceite y trapos BOAH septiembre 2023 / Reco Cero, S. A. de C. V. | C198: 22043.48
B200: Viáticos | C200: =SUM(C201:C253) -> 219492.55
A201: 5-Oct-23 | B201: SV112503 (624602) / Erick Rafael Rivera Lemus / ENS-TUX-ENS 8-14 oct23 / Boleto avión | C201: 15395
A202: 5-Oct-23 | B202: SV112503 (624602) / Erick Rafael Rivera Lemus / ENS-TUX-ENS 8-14 oct23 / Viáticos | C202: =3476.56+9266.5+8120 -> 20863.06
A203: 5-Oct-23 | B203: SV112513 (624602) / Ivan Castro Navarro / Salida Rigel 09oct23 | C203: 300
A204: 5-Oct-23 | B204: SV112514 (624602) / Juan Carlos Leñero / Salida Rigel 09oct23 | C204: 300
A205: 6-Oct-23 | B205: SV112532 (624602) / Juan Carlos Leñero / Salida Rigel 15nov23 | C205: 300
A206: 6-Oct-23 | B206: SV112534 (624602) / Ivan Castro Navarro / Salida Rigel 15nov23 | C206: 300
A207: 6-Oct-23 | B207: SV112536 (624602) / Erick Rafael Rivera Lemus / ENS-TUX-ENS 23-31oct23 / Boleto avión ida | C207: 10476
A208: 6-Oct-23 | B208: SV112536 (624602) / Erick Rafael Rivera Lemus / ENS-TUX-ENS 23-31oct23 / Viáticos | C208: 25210.99
A209: 6-Oct-23 | B209: SV112607 (624602) / Pedro Nuñez Cota / ENS-TUX-ENS 23oct-10nov23 / Boleto avión ida | C209: 8976
A210: 6-Oct-23 | B210: SV112607 (624602) / Pedro Nuñez Cota / ENS-TUX-ENS 23oct-10nov23 / Viáticos | C210: 2390
A211: 6-Oct-23 | B211: SV112614 (624602) / Marco Antonio Castillo Ramírez / ENS-TUX-ENS 23oct-10nov23 / Boleto avión | C211: 10476
A212: 6-Oct-23 | B212: SV112614 (624602) / Marco Antonio Castillo Ramírez / ENS-TUX-ENS 23oct-10nov23 / Viáticos | C212: 2390
A213: 6-Oct-23 | B213: SV112619 (624602) / Julio César Nuñez Zamudio / ENS-TUX-ENS 23oct-10nov23 / Boleto avión | C213: 10476
A214: 6-Oct-23 | B214: SV112619 (624602) / Julio César Nuñez Zamudio / ENS-TUX-ENS 23oct-10nov23 / Viáticos | C214: 2165
... A219: 9-Oct-23 | B219: SV112781 (624602) / Gustavo Castro Navarro / ENS-TUX-ENS 11-14oct23 / Boleto avión | C219: 17041
A220: 9-Oct-23 | B220: SV112781 (624602) / Gustavo Castro Navarro / ENS-TUX-ENS 11-14oct23 / Viáticos | C220: =1184+4263 -> 5447
A221: 9-Oct-23 | B221: SV112774 (624602) / Marco Antonio Castillo Ramírez / ENS-TUX-ENS 11-14oct23 / Boleto avión | C221: 17041
A222: 9-Oct-23 | B222: SV112774 (624602) / Marco Antonio Castillo Ramírez / ENS-TUX-ENS 11-14oct23 / Viáticos | C222: =1184+4263 -> 5447
A223: 9-Oct-23 | B223: SV112719 (624602) / Juan Carlos Leñero / Salida Rigel 10nov23 | C223: 300
A224: 9-Oct-23 | B224: SV112718 (624602) / Ivan Castro Navarro / Salida Rigel 10nov23 | C224: 300
A225: 9-Oct-23 | B225: SV112717 (624602) / Ivan Castro Navarro / Salida Rigel 08nov23 | C225: 300
A226: 9-Oct-23 | B226: SV112716 (624602) / Juan Carlos Leñero / Salida Rigel 08nov23 | C226: 300
...

Sheet NOV23
A2: NOVIEMBRE 2023 | C2: =C4+C76 -> 1180639.7
A3: Fecha | B3: Concepto | C3: Monto
B4: MATERIALES | C4: =C5+C8+C13+C19+C25+C32+C37+C45+C53+C57+C60+C66+C69 -> 984506.34
B5: Diesel para Buque | C5: =SUM(C6:C6) -> 968856.53
A6: 45247 | B6: SA87605 (624602) / XX,000 litros de diésel BOAH dic23 / Distribuidora de diésel Río Pánuco, S. A. de C. V. | C6: 968856.53
B8: Gasolina para embarcaciones menores | C8: =SUM(C9:C11) -> 0
B13: Gasolina para vehículos | C13: =SUM(C14:C17) -> 0
B19: Lubricantes | C19: =SUM(C20:C23) -> 0
B25: Víveres | C25: =SUM(C26:C30) -> 281.43
A26: 45243 | B26: RFF12091 (624602) / Suministro de garrafones de agua BOAH | C26: =133.31+148.12 -> 281.43
B32: Artículos y accesorios de cocina/limpieza | C32: =SUM(C33:C35) -> 4080
A33: 45243 | B33: RFF12092 (624602) / Bolsas para basura | C33: =200 -> 200
A34: 45243 | B34: RFF12091 (624602) / Materiales limpieza cocina, vasos desechables | C34: =3664+216 -> 3880
B37: Mats. Para Mantto. De Cubiertas / Casco | C37: =SUM(C38:C43) -> 319.94
A38: 45243 | B38: RFF12091 (624602) / Felpas y coladores pintura | C38: =319.94 -> 319.94
B45: Mats. Para Mantto. De Máquinas | C45: =SUM(C46:C51) -> 9036.4
A46: 45243 | B46: RFF12092 (624602) / Tornillería, niples, tanque de gas, watta, tubería y focos LED | C46: =378.07+278.01+280+98.8+1016.51+349.97 -> 2401.36
A47: 45243 | B47: RFF12091 (624602) / Hojas neopreno, cemento gris, espuma, tubos PVC | C47: =780.03+715+5000+140.01 -> 6635.04
B53: Mats. Mantto. Embarcaciones Menores | C53: =SUM(C54:C55) -> 1932.04
A54: 45243 | B54: RFF12091 (624602) / Alfombra | C54: =1120.88 -> 1120.88
A55: 45243 | B55: RFF12092 (624602) / Materiales mantto Genus apoyo Ivan a SEBLA | C55: =302.4+310.76+198 -> 811.16
B57: Materiales para Mantenimiento en Dique Seco | C57: =SUM(C58) -> 0
B60: Equipo de seguridad y ayuda a la navegación | C60: =SUM(C61:C64) -> 0
B66: Mats. para laboratorios y electrónico | C66: =C67 -> 0
B69: Otros | C69: =SUM(C70:C73) -> 0
B76: SERVICIOS | C76: =C77+C83+C87+C90+C93+C96+C99+C102+C107+C111+C115+C118+C121+C126+C129+C138+C141+C162 -> 196133.39
B77: Mantenimiento a máquinas | C77: =SUM(C78:C81) -> 4000
A78: 45243 | B78: RFF12091 (624602) / Reparación fuga AC BOAH | C78: =4000 -> 4000
B83: Mantenimiento a cubiertas/casco | C83: =SUM(C84:C85) -> 0
B87: Mantenimiento en dique seco | C87: =SUM(C88) -> 0
B90: Mantenimiento a embarcaciones menores | C90: =C91 -> 0
B93: Mantenimiento a vehículos terrestres | C93: =SUM(C94) -> 0
B96: Renta muelle | C96: =C97 -> 0
B99: Personal por Outsourcing | C99: =C100 -> 0
B102: Agenciamientos | C102: =SUM(C103:C105) -> 0
B107: Limpieza de ropa de cama | C107: =SUM(C108:C109) -> 0
B111: Seguridad y ayuda a la navegación | C111: =SUM(C112:C113) -> 91913.76
A112: 45251 | B112: SS65779 (624602) / "Refaccionamiento" de extintores BOAH / Servicios Múltiples del Sureste, S. A. de C. V. | C112: =5178.24*17.75 -> 91913.76
B115: Inspecciones ABS | C115: =C116 -> 0
B118: Mantenimiento a equipo científico y de laboratorio | C118: =SUM(C119) -> 0
B121: Comunicaciones | C121: =SUM(C122:C124) -> 9039.6
A122: 45251 | B122: SS65715 (624602) / Internet satelital Starlink para crucero Canek Nov23 / Eliasib Birzayit Mendoza Luna | C122: 9039.6
B126: Parque vehicular CICESE | C126: =SUM(C127:C127) -> 0
B129: Comisiones/Servicios financieros/Pago de derechos | C129: =SUM(C130:C136) -> 0
B138: Fletes diversos | C138: =SUM(C139) -> 1251.95
A139: 45243 | B139: RFF12091 (624602) / Envío de refacciones a Tuxpan | C139: =1251.95 -> 1251.95
B141: Viáticos | C141: =SUM(C142:C160) -> 84981
A142: 10-Nov-23 | B142: SV113003 (624602) / Marco Antonio Castillo Ramírez / ENS-TUX-ENS 21nov-07dic23 / Boleto avión | C142: 14931
A143: 10-Nov-23 | B143: SV113003 (624602) / Marco Antonio Castillo Ramírez / ENS-TUX-ENS 21nov-07dic23 / Viáticos
A144: 10-Nov-23 | B144: SV113002 (624602) / Julio César Nuñez Zamudio / ENS-TUX-ENS 21nov-08dic23 / Boleto avión | C144: 15410
A145: 10-Nov-23 | B145: SV113002 (624602) / Julio César Nuñez Zamudio / ENS-TUX-ENS 21nov-08dic23 / Viáticos
A146: 10-Nov-23 | B146: SV113001 (624602) / Gustavo Castro Navarro / ENS-TUX-ENS 21nov-08dic23 / Boleto avión | C146: 15410
A147: 10-Nov-23 | B147: SV113001 (624602) / Gustavo Castro Navarro / ENS-TUX-ENS 21nov-08dic23 / Viáticos
A148: 10-Nov-23 | B148: SV113000 (624602) / Pedro Nuñez Cota / ENS-TUX-ENS 21nov-08dic23 / Boleto avión | C148: 13910
A149: 10-Nov-23 | B149: SV113000 (624602) / Pedro Nuñez Cota / ENS-TUX-ENS 21nov-08dic23 / Viáticos
A150: 10-Nov-23 | B150: SV112999 (624602) / Carlos Enrique Ortiz de los Santos / ENS-TUX-TEP 21nov-08dic23 / Boleto avión | C150: 7102
A151: 10-Nov-23 | B151: SV112999 (624602) / Carlos Enrique Ortiz de los Santos / ENS-TUX-TEP 21nov-08dic23 / Viáticos
A152: 10-Nov-23 | B152: SV112998 (624602) / Ernesto Alonso Valenzuela Palacios / ENS-TUX-ENS 21-26nov23 / Boleto avión | C152: 18218
A153: 10-Nov-23 | B153: SV112998 (624602) / Ernesto Alonso Valenzuela Palacios / ENS-TUX-ENS 21-26nov23 / Viáticos
B162: Otros | C162: =SUM(C163:C166) -> 4947.08
A163: 45243 | B163: RFF12091 (624602) / Recolección basura BOAH, renta mobiliario noche ciencias, suministro pipa agua BOAH | C163: =2320+1119.08+1508 -> 4947.08
B169: INVERSION | C169: =SUM(C170:C174) -> 0

Sheet DIC23
A2: DICIEMBRE 2023 | C2: =C4+C54 -> 0
A3: Fecha | B3: Concepto | C3: Monto
B4: MATERIALES | C4: =C5+C8+C11+C14+C17+C21+C24+C28+C34+C38+C41+C44+C47 -> 0
B5: Diesel para Buque | C5: =SUM(C6:C6) -> 0
B8: Gasolina para embarcaciones menores | C8: =C9 -> 0
B11: Gasolina para vehículos | C11: 0
B14: Lubricantes | C14: =C15 -> 0
B17: Víveres | C17: =SUM(C18:C19) -> 0
B21: Artículos y accesorios de cocina/limpieza | C21: =SUM(C22:C22) -> 0
B24: Mats. Para Mantto. De Cubiertas / Casco | C24: =SUM(C25:C26) -> 0
B28: Mats. Para Mantto. De Máquinas | C28: =SUM(C29:C32) -> 0
B34: Mats. Mantto. Embarcaciones Menores | C34: =SUM(C35:C36) -> 0
B38: Materiales para Mantenimiento en Dique Seco | C38: =SUM(C39) -> 0
B41: Equipo de seguridad y ayuda a la navegación | C41: =C42 -> 0
B44: Mats. para laboratorios y electrónico | C44: 0
B47: Otros | C47: =SUM(C48:C51) -> 0
B54: SERVICIOS | C54: =C55+C58+C62+C65+C68+C71+C74+C77+C81+C84+C87+C90+C93+C97+C104+C110+C113+C122 -> 0
B55: Mantenimiento a máquinas | C55: =C56 -> 0
B58: Mantenimiento a cubiertas/casco | C58: =SUM(C59:C60) -> 0
B62: Mantenimiento en dique seco | C62: =SUM(C63) -> 0
B65: Mantenimiento a embarcaciones menores | C65: =C66 -> 0
B68: Mantenimiento a vehículos terrestres | C68: =SUM(C69) -> 0
B71: Renta muelle | C71: =C72 -> 0
B74: Personal por Outsourcing | C74: =C75 -> 0
B77: Agenciamientos | C77: =SUM(C78:C79) -> 0
B81: Limpieza de ropa de cama | C81: =SUM(C82:C82) -> 0
B84: Seguridad y ayuda a la navegación | C84: =SUM(C85:C85) -> 0
B87: Inspecciones ABS | C87: 0
B90: Mantenimiento a equipo científico y de laboratorio | C90: 0
B93: Comunicaciones | C93: =SUM(C94:C95) -> 0
B97: Parque vehicular CICESE | C97: =SUM(C98:C102) -> 0
B104: Comisiones/Servicios financieros/Pago de derechos | C104: =SUM(C105:C108) -> 0
B110: Fletes diversos | C110: =SUM(C111) -> 0
B113: Viáticos | C113: =SUM(C114:C120) -> 0
B122: Otros | C122: =SUM(C123:C127) -> 0
B130: INVERSION | C130: =SUM(C131:C131) -> 0

Sheet VACIADO
A1: VACIADO ANUAL 2023
B2: Enero | C2: Febrero | D2: Marzo | E2: Abril | F2: Mayo | G2: Junio | H2: Julio | I2: Agosto | J2: Septiembre | K2: Octubre | L2: Noviembre | M2: Diciembre | N2: TOTAL
A3: MATERIALES | B3: =SUM(B4:B16) -> 0 | C3: =SUM(C4:C16) -> 82962.285 | D3: =SUM(D4:D16) -> 41356.3 | E3: =SUM(E4:E16) -> 320226 | F3: =SUM(F4:F16) -> 44821.422 | G3: =SUM(G4:G16) -> 138477.37 | H3: =SUM(H4:H16) -> 42720.71 | I3: =SUM(I4:I16) -> 95058.69 | ... N3: =SUM(N4:N16) -> 2232281.8
A4: Diesel para Buque | B4: ='ENE23'!C5 -> 0 | C4: ='FEB23'!C5 -> 0 | D4: ='MAR23'!C5 -> 0 | E4: ='ABR23'!C5 -> 0 | F4: ='MAY23'!C5 -> 0 | G4: ='JUN23'!C5 -> 0 | H4: ='JUL23'!C5 -> 0 | I4: ='AGO23'!C5 -> 0 | J4: ='SEP23'!C5 -> 0 | K4: ='OCT23'!C5 -> 0 | L4: ='NOV23'!C5 -> 968856.53 | M4: ='DIC23'!C5 -> 0 | N4: =SUM(B4:M4) -> 968856.53
A5: Gasolina para embarcaciones menores | B5: ='ENE23'!C8 -> 0 | C5: ='FEB23'!C10 -> 0 | D5: ='MAR23'!C10 -> 0 | E5: ='ABR23'!C10 -> 0 | F5: ='MAY23'!C9 -> 7491.45 | G5: ='JUN23'!C11 -> 0 | H5: ='JUL23'!C10 -> 9476.46 | I5: ='AGO23'!C9 -> 0 | J5: ='SEP23'!C9 -> 2400 | K5: ='OCT23'!C9 -> 2400 | L5: ='NOV23'!C8 -> 0 | M5: ='DIC23'!C8 -> 0 | N5: =SUM(B5:M5) -> 21767.91
A6: Gasolina para vehículos | B6: ='ENE23'!C11 -> 0 | C6: ='FEB23'!C15 -> 0 | D6: ='MAR23'!C19 -> 2128.03 | E6: ='ABR23'!C18 -> 0 | F6: ='MAY23'!C18 -> 1212.72 | G6: ='JUN23'!C18 -> 0 | H6: ='JUL23'!C16 -> 5125.04 | I6: ='AGO23'!C15 -> 750.1 | J6: ='SEP23'!C15 -> 1572.2 | K6: ='OCT23'!C16 -> 4406.53 | L6: ='NOV23'!C13 -> 0 | M6: ='DIC23'!C11 -> 0 | N6: =SUM(B6:M6) -> 15194.62
A7: Lubricantes | B7: ='ENE23'!C15 -> 0 | C7: ='FEB23'!C22 -> 0 | D7: ='MAR23'!C24 -> 0 | E7: ='ABR23'!C22 -> 0 | F7: ='MAY23'!C26 -> 0 | G7: ='JUN23'!C22 -> 43200 | H7: ='JUL23'!C21 -> 0 | I7: ='AGO23'!C20 -> 0 | J7: ='SEP23'!C21 -> 0 | K7: ='OCT23'!C22 -> 0 | L7: ='NOV23'!C19 -> 0 | M7: ='DIC23'!C14 -> 0 | N7: =SUM(B7:M7) -> 43200
A8: Víveres | B8: ='ENE23'!C20 -> 0 | C8: ='FEB23'!C27 -> 51219.93 | D8: ='MAR23'!C28 -> 21315 | E8: ='ABR23'!C28 -> 300601.64 | F8: ='MAY23'!C31 -> 0 | G8: ='JUN23'!C27 -> 0 | H8: ='JUL23'!C24 -> 1119 | I8: ='AGO23'!C26 -> 59039.33 | J8: ='SEP23'!C25 -> 63719.8 | K8: ='OCT23'!C25 -> 91953.74 | L8: ='NOV23'!C25 -> 281.43 | M8: ='DIC23'!C17 -> 0 | N8: =SUM(B8:M8) -> 589249.87
A9: Artículos y accesorios de cocina/limpieza | B9: ='ENE23'!C29 -> 0 | C9: ='FEB23'!C34 -> 0 | D9: ='MAR23'!C37 -> 3584.26 | E9: ='ABR23'!C37 -> 18195.06 | F9: ='MAY23'!C40 -> 0 | G9: ='JUN23'!C35 -> 0 | H9: ='JUL23'!C31 -> 1426.48 | I9: ='AGO23'!C36 -> 6134.4 | J9: ='SEP23'!C32 -> 1841.04 | K9: ='OCT23'!C36 -> 559 | L9: ='NOV23'!C32 -> 4080 | M9: ='DIC23'!C21 -> 0 | N9: =SUM(B9:M9) -> 35820.24
A10: Mats. Para Mantto. De Cubiertas / Casco | B10: ='ENE23'!C34 -> 0 | C10: ='FEB23'!C40 -> 0 | D10: ='MAR23'!C45 -> 0 | E10: ='ABR23'!C45 -> 0 | F10: ='MAY23'!C46 -> 2300.61 | G10: ='JUN23'!C48 -> 0 | H10: ='JUL23'!C34 -> 17965.61 | I10: ='AGO23'!C44 -> 11226.41 | J10: ='SEP23'!C39 -> 12456.5 | K10: ='OCT23'!C42 -> 0 | L10: ='NOV23'!C37 -> 319.94 | M10: ='DIC23'!C24 -> 0 | N10: =SUM(B10:M10) -> 44269.07
A11: Mats. Para Mantto. De Máquinas | B11: ='ENE23'!C39 -> 0 | C11: ='FEB23'!C49 -> 22969.345 | D11: ='MAR23'!C52 -> 14329.01 | E11: ='ABR23'!C52 -> 0 | F11: ='MAY23'!C54 -> 16564.82 | G11: ='JUN23'!C55 -> 9757.93 | H11: ='JUL23'!C40 -> 7328.76 | I11: ='AGO23'!C53 -> 2950 | J11: ='SEP23'!C48 -> 18992.82 | K11: ='OCT23'!C51 -> 192458.01 | L11: ='NOV23'!C45 -> 9036.4 | M11: ='DIC23'!C28 -> 0 | N11: =SUM(B11:M11) -> 294387.1
A12: Mats. Mantto. Embarcaciones Menores | B12: ='ENE23'!C44 -> 0 | C12: ='FEB23'!C59 -> 4168.55 | D12: ='MAR23'!C60 -> 0 | E12: ='ABR23'!C61 -> 0 | F12: ='MAY23'!C63 -> 0 | G12: ='JUN23'!C65 -> 8478 | H12: ='JUL23'!C51 -> 279.36 | I12: ='AGO23'!C64 -> 1645 | J12: ='SEP23'!C57 -> 22166.376 | K12: ='OCT23'!C62 -> 11342.05 | L12: ='NOV23'!C53 -> 1932.04 | M12: ='DIC23'!C34 -> 0 | N12: =SUM(B12:M12) -> 50011.376
A13: Mats. Para Mantto. En Dique Seco | B13: ='ENE23'!C49 -> 0 | C13: ='FEB23'!C66 -> 0 | D13: ='MAR23'!C66 -> 0 | E13: ='ABR23'!C67 -> 0 | F13: ='MAY23'!C70 -> 0 | G13: ='JUN23'!C71 -> 0 | H13: ='JUL23'!C57 -> 0 | I13: ='AGO23'!C71 -> 0 | J13: ='SEP23'!C64 -> 0 | K13: ='OCT23'!C68 -> 0 | L13: ='NOV23'!C57 -> 0 | M13: ='DIC23'!C38 -> 0 | N13: =SUM(B13:M13) -> 0
A14: Equipo de seguridad y ayuda a la navegación | B14: ='ENE23'!C52 -> 0 | C14: ='FEB23'!C69 -> 0 | D14: ='MAR23'!C70 -> 0 | E14: ='ABR23'!C75 -> 0 | F14: ='MAY23'!C76 -> 11861.502 | G14: ='JUN23'!C74 -> 0 | H14: ='JUL23'!C61 -> 0 | I14: ='AGO23'!C80 -> 12287.92 | J14: ='SEP23'!C69 -> 44296.216 | K14: ='OCT23'!C73 -> 0 | L14: ='NOV23'!C60 -> 0 | M14: ='DIC23'!C41 -> 0 | N14: =SUM(B14:M14) -> 68445.638
A15: Mats. para laboratorios y electrónico | B15: ='ENE23'!C58 -> 0 | C15: ='FEB23'!C79 -> 0 | D15: ='MAR23'!C75 -> 0 | E15: ='ABR23'!C78 -> 0 | F15: ='MAY23'!C82 -> 0 | G15: ='JUN23'!C77 -> 0 | H15: ='JUL23'!C65 -> 0 | I15: ='AGO23'!C85 -> 0 | J15: ='SEP23'!C76 -> 0 | K15: ='OCT23'!C77 -> 0 | L15: ='NOV23'!C66 -> 0 | M15: ='DIC23'!C44 -> 0 | N15: =SUM(B15:M15) -> 0
A16: Otros | B16: ='ENE23'!C61 -> 0 | C16: ='FEB23'!C82 -> 4604.46 | D16: ='MAR23'!C80 -> 0 | E16: ='ABR23'!C81 -> 1429.3 | F16: ='MAY23'!C86 -> 5390.32 | G16: ='JUN23'!C80 -> 77041.44 | H16: ='JUL23'!C68 -> 0 | I16: ='AGO23'!C89 -> 1025.53 | J16: ='SEP23'!C79 -> 6272.95 | K16: ='OCT23'!C82 -> 5315.43 | L16: ='NOV23'!C69 -> 0 | M16: ='DIC23'!C47 -> 0 | N16: =SUM(B16:M16) -> 101079.43
A18: SERVICIOS | B18: =SUM(B19:B36) -> 86444.12 | C18: =SUM(C19:C36) -> 341948.28 | D18: =SUM(D19:D36) -> 786458.46 | E18: =SUM(E19:E36) -> 764099.49 | F18: =SUM(F19:F36) -> 699878.36 | G18: =SUM(G19:G36) -> 655400.38 | H18: =SUM(H19:H36) -> 141353.78 | I18: =SUM(I19:I36) -> 617890.11 | ... N18: =SUM(N19:N36) -> 7990523.1
A19: Mantto. A máquinas | B19: ='ENE23'!C69 -> 0 | C19: ='FEB23'!C93 -> 32110 | D19: ='MAR23'!C88 -> 0 | E19: ='ABR23'!C94 -> 0 | F19: ='MAY23'!C96 -> 234830.4 | G19: ='JUN23'!C91 -> 0 | H19: ='JUL23'!C75 -> 18676 | I19: ='AGO23'!C98 -> 0 | J19: ='SEP23'!C88 -> 0 | K19: ='OCT23'!C95 -> 299980 | L19: ='NOV23'!C77 -> 4000 | M19: ='DIC23'!C55 -> 0 | N19: =SUM(B19:M19) -> 589596.4
A20: Mantto. A cubiertas | B20: ='ENE23'!C73 -> 0 | C20: ='FEB23'!C101 -> 0 | D20: ='MAR23'!C95 -> 0 | E20: ='ABR23'!C102 -> 0 | F20: ='MAY23'!C103 -> 0 | G20: ='JUN23'!C97 -> 0 | H20: ='JUL23'!C80 -> 0 | I20: ='AGO23'!C105 -> 0 | J20: ='SEP23'!C95 -> 0 | K20: ='OCT23'!C102 -> 0 | L20: ='NOV23'!C83 -> 0 | M20: ='DIC23'!C58 -> 0 | N20: =SUM(B20:M20) -> 0
A21: Mantto. En Dique Seco | B21: ='ENE23'!C77 -> 0 | C21: ='FEB23'!C104 -> 0 | D21: ='MAR23'!C98 -> 0 | E21: ='ABR23'!C108 -> 0 | F21: ='MAY23'!C109 -> 0 | G21: ='JUN23'!C101 -> 0 | H21: ='JUL23'!C84 -> 0 | I21: ='AGO23'!C111 -> 0 | J21: ='SEP23'!C100 -> 0 | K21: ='OCT23'!C112 -> 0 | L21: ='NOV23'!C87 -> 0 | M21: ='DIC23'!C62 -> 0 | N21: =SUM(B21:M21) -> 0
A22: Mantto. A Embarcaciones Menores | B22: ='ENE23'!C80 -> 0 | C22: ='FEB23'!C107 -> 0 | D22: ='MAR23'!C101 -> 0 | E22: ='ABR23'!C111 -> 0 | F22: ='MAY23'!C112 -> 0 | G22: ='JUN23'!C104 -> 24667.2 | H22: ='JUL23'!C88 -> 0 | I22: ='AGO23'!C114 -> 696 | J22: ='SEP23'!C103 -> 0 | K22: ='OCT23'!C115 -> 1890 | L22: ='NOV23'!C90 -> 0 | M22: ='DIC23'!C65 -> 0 | N22: =SUM(B22:M22) -> 27253.2
A23: Mantto. A vehículos terrestres | B23: ='ENE23'!C83 -> 0 | C23: ='FEB23'!C116 -> 0 | D23: ='MAR23'!C104 -> 0 | E23: ='ABR23'!C116 -> 4958.28 | F23: ='MAY23'!C117 -> 2808 | G23: ='JUN23'!C108 -> 0 | H23: ='JUL23'!C91 -> 0 | I23: ='AGO23'!C118 -> 0 | J23: ='SEP23'!C106 -> 0 | K23: ='OCT23'!C121 -> 0 | L23: ='NOV23'!C93 -> 0 | M23: ='DIC23'!C68 -> 0 | N23: =SUM(B23:M23) -> 7766.28
A24: Renta muelle | B24: ='ENE23'!C86 -> 0 | C24: ='FEB23'!C119 -> 0 | D24: ='MAR23'!C107 -> 496154.73 | E24: ='ABR23'!C119 -> 273225.54 | F24: ='MAY23'!C120 -> 253369.62 | G24: ='JUN23'!C112 -> 107587.46 | H24: ='JUL23'!C94 -> 0 | I24: ='AGO23'!C121 -> 232481.66 | J24: ='SEP23'!C109 -> 422036.29 | K24: ='OCT23'!C124 -> 1202787.5 | L24: ='NOV23'!C96 -> 0 | M24: ='DIC23'!C71 -> 0 | N24: =SUM(B24:M24) -> 2987642.8
A25: Personal por Outsourcing | B25: ='ENE23'!C89 -> 0 | C25: ='FEB23'!C125 -> 199942.59 | D25: ='MAR23'!C111 -> 201205.49 | E25: ='ABR23'!C122 -> 400220.14 | F25: ='MAY23'!C124 -> 0 | G25: ='JUN23'!C118 -> 412899.5 | H25: ='JUL23'!C97 -> 0 | I25: ='AGO23'!C124 -> 201205.48 | J25: ='SEP23'!C115 -> 201205.5 | K25: ='OCT23'!C132 -> 804821.95 | L25: ='NOV23'!C99 -> 0 | M25: ='DIC23'!C74 -> 0 | N25: =SUM(B25:M25) -> 2421500.6
A26: Agenciamientos | B26: ='ENE23'!C92 -> 0 | C26: ='FEB23'!C129 -> 0 | D26: ='MAR23'!C114 -> 0 | E26: ='ABR23'!C126 -> 0 | F26: ='MAY23'!C127 -> 11600 | G26: ='JUN23'!C122 -> 0 | H26: ='JUL23'!C100 -> 11600 | I26: ='AGO23'!C127 -> 0 | J26: ='SEP23'!C118 -> 17400 | K26: ='OCT23'!C139 -> 0 | L26: ='NOV23'!C102 -> 0 | M26: ='DIC23'!C77 -> 0 | N26: =SUM(B26:M26) -> 40600
A27: Limpieza de ropa de cama | B27: ='ENE23'!C95 -> 0 | C27: ='FEB23'!C133 -> 0 | D27: ='MAR23'!C119 -> 0 | E27: ='ABR23'!C131 -> 0 | F27: ='MAY23'!C132 -> 2811 | G27: ='JUN23'!C126 -> 0 | H27: ='JUL23'!C106 -> 5120 | I27: ='AGO23'!C132 -> 0 | J27: ='SEP23'!C122 -> 0 | K27: ='OCT23'!C145 -> 2629 | L27: ='NOV23'!C107 -> 0 | M27: ='DIC23'!C81 -> 0 | N27: =SUM(B27:M27) -> 10560
A28: Seguridad y ayuda a la navegación | B28: ='ENE23'!C98 -> 0 | C28: ='FEB23'!C137 -> 0 | D28: ='MAR23'!C123 -> 0 | E28: ='ABR23'!C134 -> 0 | F28: ='MAY23'!C135 -> 0 | G28: ='JUN23'!C129 -> 4212 | H28: ='JUL23'!C110 -> 0 | I28: ='AGO23'!C136 -> 0 | J28: ='SEP23'!C128 -> 24635.9 | K28: ='OCT23'!C150 -> 215294.18 | L28: ='NOV23'!C111 -> 91913.76 | M28: ='DIC23'!C84 -> 0 | N28: =SUM(B28:M28) -> 336055.84
A29: Inspecciones ABS | B29: ='ENE23'!C102 -> 0 | C29: ='FEB23'!C142 -> 0 | D29: ='MAR23'!C127 -> 0 | E29: ='ABR23'!C137 -> 0 | F29: ='MAY23'!C138 -> 60774.52 | G29: ='JUN23'!C132 -> 0 | H29: ='JUL23'!C115 -> 0 | I29: ='AGO23'!C140 -> 0 | J29: ='SEP23'!C133 -> 0 | K29: ='OCT23'!C158 -> 0 | L29: ='NOV23'!C115 -> 0 | M29: ='DIC23'!C87 -> 0 | N29: =SUM(B29:M29) -> 60774.52
A30: Mantto. A equipo científico y de laboratorio | B30: ='ENE23'!C105 -> 0 | C30: ='FEB23'!C145 -> 0 | D30: ='MAR23'!C130 -> 0 | E30: ='ABR23'!C140 -> 0 | F30: ='MAY23'!C141 -> 0 | G30: ='JUN23'!C135 -> 0 | H30: ='JUL23'!C118 -> 0 | I30: ='AGO23'!C143 -> 0 | J30: ='SEP23'!C136 -> 0 | K30: ='OCT23'!C161 -> 0 | L30: ='NOV23'!C118 -> 0 | M30: ='DIC23'!C90 -> 0 | N30: =SUM(B30:M30) -> 0
A31: Comunicaciones | B31: ='ENE23'!C109 -> 2091.36 | C31: ='FEB23'!C150 -> 1145.77 | D31: ='MAR23'!C133 -> 3148.63 | E31: ='ABR23'!C144 -> 1145.98 | F31: ='MAY23'!C144 -> 1410.89 | G31: ='JUN23'!C139 -> 3044.65 | H31: ='JUL23'!C121 -> 2932.47 | I31: ='AGO23'!C147 -> 28361.57 | J31: ='SEP23'!C139 -> 2565.95 | K31: ='OCT23'!C165 -> 6886.38 | L31: ='NOV23'!C121 -> 9039.6 | M31: ='DIC23'!C93 -> 0 | N31: =SUM(B31:M31) -> 61773.25
A32: Parque vehicular CICESE | B32: ='ENE23'!C115 -> 1800 | C32: ='FEB23'!C168 -> 3586.72 | D32: ='MAR23'!C142 -> 7235.59 | E32: ='ABR23'!C153 -> 7090.07 | F32: ='MAY23'!C153 -> 2661.29 | G32: ='JUN23'!C147 -> 3300 | H32: ='JUL23'!C128 -> 2000 | I32: ='AGO23'!C155 -> 3381.5 | J32: ='SEP23'!C149 -> 5844.78 | K32: ='OCT23'!C174 -> 8546.33 | L32: ='NOV23'!C126 -> 0 | M32: ='DIC23'!C97 -> 0 | N32: =SUM(B32:M32) -> 45446.28
A33: Comisiones/Servicios Financieros/Derechos | B33: ='ENE23'!C118 -> 218.76 | C33: ='FEB23'!C175 -> 4698 | D33: ='MAR23'!C151 -> 3284.6 | E33: ='ABR23'!C162 -> 0 | F33: ='MAY23'!C159 -> 69215.44 | G33: ='JUN23'!C152 -> 435.4 | H33: ='JUL23'!C133 -> 13581.62 | I33: ='AGO23'!C161 -> 14833.87 | J33: ='SEP23'!C155 -> 31126.37 | K33: ='OCT23'!C185 -> 10828.7 | L33: ='NOV23'!C129 -> 0 | M33: ='DIC23'!C104 -> 0 | N33: =SUM(B33:M33) -> 148222.76
A34: Fletes diversos | B34: ='ENE23'!C124 -> 0 | C34: ='FEB23'!C182 -> 18699.2 | D34: ='MAR23'!C159 -> 0 | E34: ='ABR23'!C169 -> 0 | F34: ='MAY23'!C165 -> 0 | G34: ='JUN23'!C162 -> 0 | H34: ='JUL23'!C143 -> 1451.42 | I34: ='AGO23'!C169 -> 11628.68 | J34: ='SEP23'!C164 -> 15875.35 | K34: ='OCT23'!C197 -> 22043.48 | L34: ='NOV23'!C138 -> 1251.95 | M34: ='DIC23'!C110 -> 0 | N34: =SUM(B34:M34) -> 70950.08
A35: Viáticos | B35: ='ENE23'!C128 -> 82334 | C35: ='FEB23'!C187 -> 81766 | D35: ='MAR23'!C164 -> 63365.42 | E35: ='ABR23'!C174 -> 77459.48 | F35: ='MAY23'!C170 -> 58402 | G35: ='JUN23'!C167 -> 99254.17 | H35: ='JUL23'!C147 -> 74296.02 | I35: ='AGO23'!C172 -> 121473.35 | J35: ='SEP23'!C170 -> 179578.56 | K35: ='OCT23'!C200 -> 219492.55 | L35: ='NOV23'!C141 -> 84981 | M35: ='DIC23'!C113 -> 0 | N35: =SUM(B35:M35) -> 1142402.6
A36: Otros | B36: ='ENE23'!C146 -> 0 | C36: ='FEB23'!C213 -> 0 | D36: ='MAR23'!C192 -> 12064 | E36: ='ABR23'!C215 -> 0 | F36: ='MAY23'!C197 -> 1995.2 | G36: ='JUN23'!C204 -> 0 | H36: ='JUL23'!C175 -> 11696.25 | I36: ='AGO23'!C200 -> 3828 | J36: ='SEP23'!C201 -> 3128 | K36: ='OCT23'!C255 -> 2320 | L36: ='NOV23'!C162 -> 4947.08 | M36: ='DIC23'!C122 -> 0 | N36: =SUM(B36:M36) -> 39978.53
A38: INVERSION | B38: ='ENE23'!C153 -> 0 | C38: ='FEB23'!C225 -> 0 | D38: ='MAR23'!C201 -> 0 | E38: ='ABR23'!C224 -> 0 | F38: ='MAY23'!C205 -> 12694.968 | G38: ='JUN23'!C214 -> 0 | H38: ='JUL23'!C182 -> 0 | I38: ='AGO23'!C209 -> 0 | J38: ='SEP23'!C211 -> 0 | K38: ='OCT23'!C265 -> 0 | L38: ='NOV23'!C169 -> 0 | M38: ='DIC23'!C130 -> 0 | N38: =SUM(B38:M38) -> 12694.968
A40: TOTAL DE GASTOS MENSUALES | B40: =B3+B18+B38 -> 86444.12 | C40: =C3+C18+C38 -> 424910.57 | D40: =D3+D18+D38 -> 827814.76 | E40: =E3+E18+E38 -> 1084325.5 | F40: =F3+F18+F38 -> 757394.75 | G40: =G3+G18+G38 -> 793877.75 | H40: =H3+H18+H38 -> 184074.49 | I40: =I3+I18+I38 -> 712948.8 | ... M40: =M3+M18+M38 -> 0 | N40: =SUM(B40:M40) -> 10235500

Sheet Asignaciones
A1: Asignaciones del año 2023 a las cuentas del DEO
A3: Fecha | B3: Cantidad | C3: Cuenta
A4: 23-Ene-23 | B4: 500000 | C4: 624108
A5: 23-Ene-23 | B5: 1476648.7 | C5: 624108
A6: 12-Abr-23 | B6: 660000 | C6: 624108
A7: 28-Abr-23 | B7: 700000 | C7: 624108
A8: 45113 | B8: 2891780 | C8: 624602
A9: 31-Ago-23 | B9: 2194251.6 | C9: 624602
A10: 18-Oct-23 | B10: 886293 | C10: 624602
A41: TOTAL ASIGNADO | B41: =SUM(B4:B40) -> 9308973.3
A42: BOLSA 2023 FISCAL | B42: 3000000
A43: POR ASIGNAR | B43: =B42-B41 -> -6308973.3
A45: DISPONIBLE | B45: =B41-VACIADO!N40 -> -926526.52
